{
  "name": "SaludLongevidad",
  "handle": "@SaludLongevidad-e3i",
  "type": "longform",
  "content_type": "narrated_educational",
  "language": "en",
  "niche": "Longevity, health and wellness backed by science — educational documentaries",
  "tone": "Informative, rigorous, accessible. Like a Netflix health documentary.",
  "duration_minutes": 12,
  "format": "landscape",
  "topics": [
    "intermittent fasting real effects",
    "gut microbiome and longevity",
    "deep sleep and cellular regeneration",
    "Blue Zones secrets of longevity",
    "anti-inflammatory foods science",
    "minimum effective exercise studies",
    "chronic stress effects on the body",
    "supplements with real scientific evidence",
    "telomeres and aging explained",
    "meditation brain changes proven",
    "Harvard Mediterranean diet studies",
    "hydration myths vs science",
    "cortisol and belly fat connection",
    "neuroplasticity and healthy habits",
    "vitamin D deficiency epidemic"
  ],
  "voice": "en-US-GuyNeural",
  "refresh_token_env": "YT_TOKEN_SALUD",
  "category_id": "26",
  "default_tags": [
    "salud",
    "longevidad",
    "bienestar",
    "ciencia",
    "nutrición",
    "ejercicio",
    "documental salud",
    "vida sana"
  ],
  "thumbnail_style": "clean medical aesthetic, green accent, scientific diagram, health documentary",
  "web_url": "https://saludlongevidad.org",
  "cta_description": "\n\n📖 Full article: https://saludlongevidad.org\n📩 Free newsletter: https://eepurl.com/c_iwJy-3pL\n👍 Subscribe and hit the 🔔"
}