[
  {
    "id": 2000,
    "title": "Jeanne Calment 122 Años: Análisis Cientifico Centenaria Verificada",
    "primary_keyword": "jeanne calment longevidad",
    "secondary_keywords": ["calment 122 años", "supercentenarios verificados", "jeanne calment dieta"],
    "search_intent": "informational",
    "estimated_volume": "medium",
    "estimated_difficulty": "low",
    "outline": ["H2: Quién fue Jeanne Calment", "H2: Estilo de vida y dieta documentada", "H2: Análisis genético posterior", "H2: Controversia Zak 2019", "H2: Lecciones aplicables", "H2: FAQ"],
    "key_points": ["Calment murió 1997 a los 122 años 164 días", "Consumía 1kg chocolate semanal y aceite oliva", "Bebía vino Porto diario hasta los 117", "Dejó tabaco a los 117 años", "Caminaba en bicicleta hasta los 100"],
    "internal_link_suggestions": ["centenarios verificados blue zones"],
    "amazon_product_categories": ["Aceite oliva virgen extra", "Chocolate negro 85%"],
    "monetization_intent": "both",
    "schema_type": "Article",
    "estimated_word_count": 2400,
    "eeat_signal": "Datos GRG Gerontology Research Group, biografía Allard 1998"
  },
  {
    "id": 2001,
    "title": "Resveratrol 500mg Diarios: Dosis Real Según Estudios Sinclair 2013",
    "primary_keyword": "resveratrol 500mg dosis",
    "secondary_keywords": ["resveratrol cuanto tomar", "resveratrol biodisponibilidad", "trans resveratrol mejor marca"],
    "search_intent": "transactional",
    "estimated_volume": "high",
    "estimated_difficulty": "medium",
    "outline": ["H2: Qué es el resveratrol", "H2: Estudios Sinclair Cell 2013 SIRT1", "H2: Dosis efectiva 500-1000mg", "H2: Biodisponibilidad y absorción con grasa", "H2: Marcas trans-resveratrol puras", "H2: Efectos secundarios", "H2: FAQ"],
    "key_points": ["Sinclair Cell 2013 demostró activación SIRT1", "Trans-resveratrol biodisponible 70% más", "Tomar con grasa para absorción", "Dosis humana extrapolada 500-1000mg", "Vida media 9-14 horas"],
    "internal_link_suggestions": ["protocolo sinclair completo"],
    "amazon_product_categories": ["Resveratrol suplemento", "Trans-resveratrol cápsulas"],
    "monetization_intent": "affiliate_high",
    "schema_type": "Review",
    "estimated_word_count": 2800,
    "eeat_signal": "Sinclair Cell 2013, Baur Nature 2006"
  },
  {
    "id": 2002,
    "title": "Fisetin Senolytico: Protocolo 1500mg Mayo Clinic 2018 Validado",
    "primary_keyword": "fisetin senolitico dosis",
    "secondary_keywords": ["fisetin protocolo mayo clinic", "fisetin vs quercetina", "fisetin 1500mg"],
    "search_intent": "transactional",
    "estimated_volume": "medium",
    "estimated_difficulty": "medium",
    "outline": ["H2: Qué son los senolíticos", "H2: Estudio Mayo Clinic Yousefzadeh 2018", "H2: Protocolo 1500mg 2 días al mes", "H2: Fisetin vs Dasatinib+Quercetina", "H2: Marcas y biodisponibilidad", "H2: FAQ"],
    "key_points": ["Mayo Clinic EBioMedicine 2018 demostró eficacia", "Protocolo: 1500mg/día durante 2 días al mes", "Reduce células zombie senescentes 25-50%", "Más seguro que dasatinib", "Liposomal mejora absorción 27x"],
    "internal_link_suggestions": ["senolitos dasatinib quercetina"],
    "amazon_product_categories": ["Fisetin suplemento", "Fisetin liposomal"],
    "monetization_intent": "affiliate_high",
    "schema_type": "HowTo",
    "estimated_word_count": 2600,
    "eeat_signal": "Yousefzadeh EBioMedicine 2018, Kirkland Mayo Clinic"
  },
  {
    "id": 2003,
    "title": "Urolitina A 500mg: Mitofagia Mitocondrial Estudio Nature 2019",
    "primary_keyword": "urolitina a suplemento",
    "secondary_keywords": ["urolitina a mitopure", "urolitina a beneficios", "urolitina a dosis"],
    "search_intent": "transactional",
    "estimated_volume": "medium",
    "estimated_difficulty": "medium",
    "outline": ["H2: Qué es la urolitina A", "H2: Estudio Andreux Nature Metabolism 2019", "H2: Mitofagia y reciclaje mitocondrial", "H2: Dosis 500mg vs granada natural", "H2: Mitopure Amazentis vs alternativas", "H2: FAQ"],
    "key_points": ["Andreux Nature Metabolism 2019 dosis 500-1000mg", "Solo 40% personas convierten ellagitaninos", "500mg = 6L jugo granada", "Mejora función muscular ancianos 12%", "Mitopure única forma testada clínicamente"],
    "internal_link_suggestions": ["coq10 ubiquinol vs ubiquinone"],
    "amazon_product_categories": ["Urolitina A suplemento", "Granada extracto"],
    "monetization_intent": "affiliate_high",
    "schema_type": "Review",
    "estimated_word_count": 2700,
    "eeat_signal": "Andreux Nature Metabolism 2019, Amazentis EPFL"
  },
  {
    "id": 2004,
    "title": "Espermidina 1mg vs 5mg: Autofagia Madeo Nature 2018",
    "primary_keyword": "espermidina suplemento",
    "secondary_keywords": ["espermidina autofagia", "espermidina trigo germen", "espermidina dosis longevidad"],
    "search_intent": "transactional",
    "estimated_volume": "medium",
    "estimated_difficulty": "medium",
    "outline": ["H2: Qué es la espermidina", "H2: Estudio Madeo Nature Medicine 2016", "H2: Activación autofagia celular", "H2: Dosis 1mg vs 5mg vs 15mg", "H2: Trigo germinado vs suplemento", "H2: FAQ"],
    "key_points": ["Madeo Nature Medicine 2016 redujo mortalidad", "1mg/día reduce mortalidad cardiovascular", "Trigo germen 2.4mg por 100g", "Estudio austriaco 829 personas", "Compatible con NMN y resveratrol"],
    "internal_link_suggestions": ["nmn nr longevidad"],
    "amazon_product_categories": ["Espermidina suplemento", "Trigo germinado polvo"],
    "monetization_intent": "affiliate_high",
    "schema_type": "Review",
    "estimated_word_count": 2500,
    "eeat_signal": "Madeo Nature Medicine 2016, Eisenberg Aging Cell 2009"
  },
  {
    "id": 2005,
    "title": "Quercetina 500mg: Dosis Senolitica Hidratada vs Anhidra",
    "primary_keyword": "quercetina 500mg dosis",
    "secondary_keywords": ["quercetina con bromelina", "quercetina dihidrato vs anhidra", "quercetina antiinflamatoria"],
    "search_intent": "transactional",
    "estimated_volume": "high",
    "estimated_difficulty": "medium",
    "outline": ["H2: Qué es la quercetina", "H2: Biodisponibilidad anhidra vs dihidrato", "H2: Sinergia con bromelina", "H2: Protocolo senolítico Kirkland", "H2: Mejores marcas Amazon ES", "H2: FAQ"],
    "key_points": ["Quercetina anhidra 5x más biodisponible", "Bromelina mejora absorción 50%", "Protocolo Mayo Clinic 1000mg/día 3 días", "Vida media 17 horas", "Cebolla cruda solo 20mg/100g"],
    "internal_link_suggestions": ["fisetin senolitico"],
    "amazon_product_categories": ["Quercetina con bromelina", "Quercetina anhidra"],
    "monetization_intent": "affiliate_high",
    "schema_type": "Review",
    "estimated_word_count": 2700,
    "eeat_signal": "Kirkland EBioMedicine 2018, Boots Toxicology 2003"
  },
  {
    "id": 2006,
    "title": "EGCG Té Verde 300mg: Dosis Polifenol Hepatotoxicidad",
    "primary_keyword": "egcg dosis té verde",
    "secondary_keywords": ["egcg suplemento longevidad", "té verde matcha cuanto tomar", "egcg hepatotoxicidad limites"],
    "search_intent": "transactional",
    "estimated_volume": "high",
    "estimated_difficulty": "medium",
    "outline": ["H2: Qué es el EGCG", "H2: Dosis efectiva 300mg/día", "H2: Riesgo hepatotoxicidad >800mg", "H2: EGCG vs té verde tradicional", "H2: Mejores marcas certificadas", "H2: FAQ"],
    "key_points": ["EFSA 2018 limita 800mg/día por hepatotoxicidad", "300mg = 5-6 tazas té verde", "Mejor con vitamina C para absorción", "Activa AMPK como metformina", "Matcha ceremonial 137mg EGCG/g"],
    "internal_link_suggestions": ["polifenoles longevidad antioxidantes"],
    "amazon_product_categories": ["EGCG suplemento", "Matcha ceremonial"],
    "monetization_intent": "affiliate_high",
    "schema_type": "Review",
    "estimated_word_count": 2400,
    "eeat_signal": "EFSA Journal 2018, Yang Chem Res Toxicol 2010"
  },
  {
    "id": 2007,
    "title": "PQQ 20mg Mitocondrial: Biogénesis vs CoQ10 Comparativa Clínica",
    "primary_keyword": "pqq mitocondrial suplemento",
    "secondary_keywords": ["pqq vs coq10", "pqq biogenesis mitocondrial", "pyrroloquinoline quinone dosis"],
    "search_intent": "comparative",
    "estimated_volume": "low",
    "estimated_difficulty": "low",
    "outline": ["H2: Qué es PQQ", "H2: Biogénesis mitocondrial nueva", "H2: PQQ vs CoQ10 mecanismos", "H2: Dosis 10-20mg/día", "H2: Sinergia con ubiquinol", "H2: FAQ"],
    "key_points": ["Chowanadisai J Biol Chem 2010 mostró biogénesis", "PQQ crea nuevas mitocondrias, CoQ10 alimenta existentes", "Dosis 10-20mg/día", "Vida media 60 horas", "Stack con ubiquinol potencia ATP"],
    "internal_link_suggestions": ["coq10 ubiquinol vs ubiquinone"],
    "amazon_product_categories": ["PQQ suplemento", "PQQ con CoQ10"],
    "monetization_intent": "affiliate_high",
    "schema_type": "Review",
    "estimated_word_count": 2600,
    "eeat_signal": "Chowanadisai J Biol Chem 2010, Stites J Nutr 2006"
  },
  {
    "id": 2008,
    "title": "CoQ10 Ubiquinol vs Ubiquinone: Bioequivalencia y Edad",
    "primary_keyword": "coq10 ubiquinol ubiquinone diferencia",
    "secondary_keywords": ["ubiquinol kaneka", "coq10 mejor forma", "ubiquinol mayores 40 años"],
    "search_intent": "comparative",
    "estimated_volume": "high",
    "estimated_difficulty": "medium",
    "outline": ["H2: Qué es la coenzima Q10", "H2: Ubiquinol forma reducida activa", "H2: Capacidad reducción declina edad", "H2: Estudio Langsjoen 2008", "H2: Kaneka QH vs alternativas", "H2: FAQ"],
    "key_points": ["Ubiquinol 8x más biodisponible >40 años", "Capacidad reducción cae 50% a los 60", "Langsjoen Biofactors 2008", "Estatinas reducen CoQ10 endógeno 40%", "Kaneka QH único patentado humano"],
    "internal_link_suggestions": ["pqq mitocondrial"],
    "amazon_product_categories": ["Ubiquinol Kaneka", "CoQ10 con omega-3"],
    "monetization_intent": "affiliate_high",
    "schema_type": "Review",
    "estimated_word_count": 2900,
    "eeat_signal": "Langsjoen Biofactors 2008, Hosoe Regul Toxicol 2007"
  },
  {
    "id": 2009,
    "title": "Sardinia Zona Azul: Dieta Pastores Centenarios Buettner 2008",
    "primary_keyword": "sardinia zona azul dieta",
    "secondary_keywords": ["centenarios sardinia barbagia", "dieta sarda longevidad", "buettner zonas azules"],
    "search_intent": "informational",
    "estimated_volume": "medium",
    "estimated_difficulty": "low",
    "outline": ["H2: Qué son las Blue Zones Buettner", "H2: Provincia Nuoro Barbagia", "H2: Dieta pastoril mediterránea", "H2: Vino Cannonau polifenoles", "H2: Genética y comunidad", "H2: FAQ"],
    "key_points": ["Buettner National Geographic 2005", "Sardinia 1 centenario por 196 personas", "Dieta: pan carasau, queso pecorino, leche oveja", "Vino Cannonau 3x polifenoles que normal", "Caminata diaria 8km terreno montañoso"],
    "internal_link_suggestions": ["okinawa ikigai longevidad"],
    "amazon_product_categories": ["Aceite oliva sardinia", "Vino Cannonau"],
    "monetization_intent": "both",
    "schema_type": "Article",
    "estimated_word_count": 2800,
    "eeat_signal": "Buettner National Geographic 2005, Pes Exp Gerontol 2013"
  },
  {
    "id": 2010,
    "title": "Okinawa Ikigai: Hara Hachi Bu y Centenarios Japoneses",
    "primary_keyword": "okinawa hara hachi bu",
    "secondary_keywords": ["ikigai longevidad okinawa", "okinawa diet centenarios", "okinawa restricción calorica"],
    "search_intent": "informational",
    "estimated_volume": "high",
    "estimated_difficulty": "medium",
    "outline": ["H2: Qué es Hara Hachi Bu", "H2: Concepto Ikigai propósito vital", "H2: Dieta tradicional 1200 kcal", "H2: Boniato morado batata", "H2: Moais comunidad social", "H2: FAQ"],
    "key_points": ["Hara Hachi Bu: comer hasta 80% saciedad", "Restricción calórica natural 20%", "Boniato morado 60% calorías diarias", "Suntory Wellness Okinawa Centenarian Study", "Moais grupos vitalicios apoyo"],
    "internal_link_suggestions": ["sardinia zona azul"],
    "amazon_product_categories": ["Boniato morado", "Té sanpin Okinawa"],
    "monetization_intent": "both",
    "schema_type": "Article",
    "estimated_word_count": 3000,
    "eeat_signal": "Willcox JACN 2014, Suzuki Asian Med J 2001"
  },
  {
    "id": 2011,
    "title": "Loma Linda Adventistas: Vegetarianismo y Vida Promedio +10 Años",
    "primary_keyword": "loma linda adventistas longevidad",
    "secondary_keywords": ["adventistas séptimo día dieta", "loma linda zona azul california", "estudio adventist health"],
    "search_intent": "informational",
    "estimated_volume": "medium",
    "estimated_difficulty": "low",
    "outline": ["H2: Quiénes son los Adventistas", "H2: Adventist Health Study-2", "H2: Dieta vegetariana lacto-ovo", "H2: Frutos secos diarios", "H2: Sábado descanso semanal", "H2: FAQ"],
    "key_points": ["Adventistas viven 10 años más promedio", "Loma Linda University 96000 participantes", "Frutos secos 5x semana = -40% cardiopatía", "Vegetarianos -25% mortalidad total", "Fraser JAMA Intern Med 2013"],
    "internal_link_suggestions": ["dieta mediterránea longevidad"],
    "amazon_product_categories": ["Frutos secos mix", "Almendras crudas"],
    "monetization_intent": "both",
    "schema_type": "Article",
    "estimated_word_count": 2700,
    "eeat_signal": "Fraser JAMA Intern Med 2013, Adventist Health Study-2"
  },
  {
    "id": 2012,
    "title": "DHEA 25mg Mujer 50mg Hombre: Hormona Suprarrenal Decline",
    "primary_keyword": "dhea suplemento dosis",
    "secondary_keywords": ["dhea hombre vs mujer", "dhea anti envejecimiento", "dhea contraindicaciones"],
    "search_intent": "transactional",
    "estimated_volume": "medium",
    "estimated_difficulty": "high",
    "outline": ["H2: Qué es la DHEA", "H2: Declive 80% a los 70 años", "H2: Dosis hombre 50mg vs mujer 25mg", "H2: Estudio DHEAge Baulieu PNAS 2000", "H2: Riesgos hormonas", "H2: FAQ"],
    "key_points": ["DHEA-S pico 25 años, cae 80% a los 70", "Baulieu PNAS 2000 estudio 280 personas", "Hombres 50mg/noche, mujeres 25mg", "Convertible a testosterona y estrógeno", "Análisis previo obligatorio"],
    "internal_link_suggestions": ["pregnenolona hormona madre"],
    "amazon_product_categories": ["DHEA 25mg cápsulas", "DHEA 50mg hombre"],
    "monetization_intent": "affiliate_high",
    "schema_type": "Review",
    "estimated_word_count": 2900,
    "eeat_signal": "Baulieu PNAS 2000, Labrie JCEM 2003"
  },
  {
    "id": 2013,
    "title": "Pregnenolona 30mg: Madre Hormonas Memoria Sueño",
    "primary_keyword": "pregnenolona dosis suplemento",
    "secondary_keywords": ["pregnenolona memoria", "pregnenolona vs dhea", "pregnenolona insomnio"],
    "search_intent": "transactional",
    "estimated_volume": "low",
    "estimated_difficulty": "low",
    "outline": ["H2: Qué es la pregnenolona", "H2: Madre de todas las hormonas esteroides", "H2: Dosis 10-50mg", "H2: Mejora memoria adultos mayores", "H2: Efectos sueño profundo", "H2: FAQ"],
    "key_points": ["Pregnenolona precursor DHEA, cortisol, progesterona", "Caída 60% a los 75 años", "Vallee Frontiers Endocrinol 2014", "Aumenta GABA receptores sueño profundo", "Dosis matutina 30mg típica"],
    "internal_link_suggestions": ["dhea suplemento longevidad"],
    "amazon_product_categories": ["Pregnenolona suplemento"],
    "monetization_intent": "affiliate_high",
    "schema_type": "Review",
    "estimated_word_count": 2400,
    "eeat_signal": "Vallee Frontiers Endocrinol 2014, Roberts Brain Res 2002"
  },
  {
    "id": 2014,
    "title": "Hormona Crecimiento Natural: Sueño Ayuno Ejercicio HIIT",
    "primary_keyword": "hormona crecimiento natural",
    "secondary_keywords": ["aumentar gh natural", "hormona crecimiento ayuno", "hgh sueño profundo"],
    "search_intent": "informational",
    "estimated_volume": "high",
    "estimated_difficulty": "medium",
    "outline": ["H2: Qué es la hormona crecimiento", "H2: Pulso sueño profundo 70%", "H2: Ayuno 24h aumenta HGH 1300%", "H2: HIIT vs cardio steady state", "H2: Aminoácidos arginina lisina", "H2: FAQ"],
    "key_points": ["GH cae 14% por década desde 30 años", "Sueño profundo NREM produce 70% pulso", "Ayuno 24h: HGH +1300% mujeres, +2000% hombres", "Veldhuis JCEM 1995", "HIIT supera cardio en liberación GH"],
    "internal_link_suggestions": ["sueño profundo nrem", "ayuno intermitente 16 8"],
    "amazon_product_categories": ["L-arginina", "L-lisina suplemento"],
    "monetization_intent": "both",
    "schema_type": "HowTo",
    "estimated_word_count": 2800,
    "eeat_signal": "Veldhuis JCEM 1995, Hartman JCEM 1992"
  },
  {
    "id": 2015,
    "title": "Cronotipo DMS: Sincronizar Sueño REM Walker 2017",
    "primary_keyword": "cronobiologia sueño dms",
    "secondary_keywords": ["dim light melatonin onset", "cronotipo búho alondra", "ritmo circadiano sueño"],
    "search_intent": "informational",
    "estimated_volume": "medium",
    "estimated_difficulty": "medium",
    "outline": ["H2: Qué es DLMO/DMS", "H2: Cronotipos genéticos PER3", "H2: REM vs NREM funciones", "H2: Walker Why We Sleep 2017", "H2: Cómo medir tu cronotipo", "H2: FAQ"],
    "key_points": ["DLMO inicio melatonina nocturna", "PER3 gen determina cronotipo", "Walker Why We Sleep 2017", "REM consolida memoria emocional", "Búhos riesgo mortalidad +10% Knutson"],
    "internal_link_suggestions": ["melatonina dosis adultos"],
    "amazon_product_categories": ["Reloj despertador luz", "Anteojos azul block"],
    "monetization_intent": "both",
    "schema_type": "Article",
    "estimated_word_count": 2900,
    "eeat_signal": "Walker Why We Sleep 2017, Knutson Chronobiol Int 2018"
  },
  {
    "id": 2016,
    "title": "Sauna Finlandesa Protocolo: 4 Sesiones Semana -50% Mortalidad",
    "primary_keyword": "sauna finlandesa beneficios",
    "secondary_keywords": ["sauna mortalidad cardiovascular", "protocolo sauna longevidad", "sauna laukkanen estudio"],
    "search_intent": "informational",
    "estimated_volume": "medium",
    "estimated_difficulty": "low",
    "outline": ["H2: Estudio KIHD Finlandia 2315 hombres", "H2: 4-7 sesiones reducen mortalidad 50%", "H2: Mecanismo proteínas shock térmico", "H2: Protocolo 80-100°C 20 min", "H2: Sauna infrarroja vs tradicional", "H2: FAQ"],
    "key_points": ["Laukkanen JAMA Intern Med 2015", "4-7 sesiones/semana = -50% mortalidad", "Cada sesión 20 min mínimo", "HSP70 proteínas shock térmico", "Equivalente cardiovascular ejercicio moderado"],
    "internal_link_suggestions": ["cold exposure plunge protocolo"],
    "amazon_product_categories": ["Sauna infrarroja portátil", "Sauna manta infrarroja"],
    "monetization_intent": "both",
    "schema_type": "HowTo",
    "estimated_word_count": 2700,
    "eeat_signal": "Laukkanen JAMA Intern Med 2015, KIHD Kuopio Study"
  },
  {
    "id": 2017,
    "title": "Cold Plunge 11min Semana: Soberg Huberman Protocol Real",
    "primary_keyword": "cold plunge protocolo huberman",
    "secondary_keywords": ["baño frío 11 minutos", "cold exposure longevidad", "soberg cold therapy"],
    "search_intent": "informational",
    "estimated_volume": "high",
    "estimated_difficulty": "medium",
    "outline": ["H2: Origen 11 minutos Soberg 2021", "H2: Norepinefrina x5 baseline", "H2: Grasa marrón activación", "H2: Protocolo 3-4 sesiones semana", "H2: Wim Hof breathing", "H2: FAQ"],
    "key_points": ["Soberg Cell Reports Med 2021", "11 min/semana total dividido sesiones", "Temperatura 12°C o menor", "Norepinefrina aumenta 530%", "Activa BAT grasa marrón termogenesis"],
    "internal_link_suggestions": ["sauna finlandesa protocolo"],
    "amazon_product_categories": ["Bañera cold plunge", "Bolsas gel hielo"],
    "monetization_intent": "both",
    "schema_type": "HowTo",
    "estimated_word_count": 2600,
    "eeat_signal": "Soberg Cell Reports Med 2021, Huberman Stanford"
  },
  {
    "id": 2018,
    "title": "Meditación MBSR 8 Semanas: Reducción Telómeros Blackburn",
    "primary_keyword": "mbsr meditacion 8 semanas",
    "secondary_keywords": ["mindfulness telomeros estudio", "kabat zinn mbsr", "meditacion longevidad blackburn"],
    "search_intent": "informational",
    "estimated_volume": "medium",
    "estimated_difficulty": "medium",
    "outline": ["H2: Qué es MBSR Kabat-Zinn", "H2: Programa 8 semanas estructura", "H2: Estudio Blackburn telómeros 2009", "H2: Retiro meditación 3 meses Jacobs", "H2: Cómo empezar MBSR online gratis", "H2: FAQ"],
    "key_points": ["Kabat-Zinn UMass 1979", "Blackburn Nobel 2009 telomerasa", "Jacobs Psychoneuroendocrinology 2011 retiro 3 meses", "Telomerasa +30% en meditadores", "Programa 8 semanas, 45 min diarios"],
    "internal_link_suggestions": ["telomeros longevidad blackburn"],
    "amazon_product_categories": ["Cojin meditación zafu", "Libro Kabat-Zinn"],
    "monetization_intent": "both",
    "schema_type": "HowTo",
    "estimated_word_count": 3000,
    "eeat_signal": "Blackburn Nobel 2009, Jacobs Psychoneuroendocrinology 2011"
  },
  {
    "id": 2019,
    "title": "Akkermansia Muciniphila: Microbiota Magra Probiótico Cantley",
    "primary_keyword": "akkermansia muciniphila probiotico",
    "secondary_keywords": ["akkermansia obesidad microbiota", "akkermansia pasteurizada cantley", "pendulum akkermansia"],
    "search_intent": "transactional",
    "estimated_volume": "low",
    "estimated_difficulty": "low",
    "outline": ["H2: Qué es Akkermansia muciniphila", "H2: Estudio Cantley Nature 2019", "H2: Pasteurizada vs viva", "H2: Marca Pendulum Glucose Control", "H2: Combinación con prebióticos polifenoles", "H2: FAQ"],
    "key_points": ["Akkermansia 3-5% microbiota personas magras", "Cantley Nature Medicine 2019 humanos", "Forma pasteurizada Amuc_1100 más eficaz", "Pendulum único producto FDA", "Polifenoles aumentan Akkermansia 5x"],
    "internal_link_suggestions": ["microbiota personalizada test"],
    "amazon_product_categories": ["Probiótico Akkermansia", "Pendulum Akkermansia"],
    "monetization_intent": "affiliate_high",
    "schema_type": "Review",
    "estimated_word_count": 2500,
    "eeat_signal": "Cantley Nature Medicine 2019, Cani Nat Rev Endocrinol"
  },
  {
    "id": 2020,
    "title": "Lactobacillus Rhamnosus GG: Eje Intestino Cerebro Cryan",
    "primary_keyword": "lactobacillus rhamnosus gg",
    "secondary_keywords": ["psicobioticos cryan", "rhamnosus cerebro intestino", "probiotico ansiedad"],
    "search_intent": "transactional",
    "estimated_volume": "medium",
    "estimated_difficulty": "medium",
    "outline": ["H2: Qué es Lactobacillus rhamnosus GG", "H2: Eje intestino-cerebro vagus", "H2: Cryan Nature Reviews 2012", "H2: Reducción cortisol y ansiedad", "H2: Mejores marcas con CFU verificados", "H2: FAQ"],
    "key_points": ["Cryan Nature Reviews Neurosci 2012 acuñó psicobióticos", "L. rhamnosus GG cepa más estudiada", "Modula GABA cerebro vía vago", "10-20 mil millones CFU dosis efectiva", "Refrigerar mantiene viabilidad"],
    "internal_link_suggestions": ["akkermansia muciniphila"],
    "amazon_product_categories": ["Probiótico Lactobacillus GG", "Yogur kefir LGG"],
    "monetization_intent": "affiliate_high",
    "schema_type": "Review",
    "estimated_word_count": 2700,
    "eeat_signal": "Cryan Nature Rev Neurosci 2012, Bravo PNAS 2011"
  },
  {
    "id": 2021,
    "title": "Dasatinib + Quercetina: Senolítico Original Kirkland 2018",
    "primary_keyword": "dasatinib quercetina senolitico",
    "secondary_keywords": ["d+q protocolo kirkland", "senolitico dasatinib mayo clinic", "dasatinib quercetina humanos"],
    "search_intent": "informational",
    "estimated_volume": "low",
    "estimated_difficulty": "low",
    "outline": ["H2: Qué son los senolíticos", "H2: Estudio Zhu Aging Cell 2015", "H2: Mayo Clinic ensayo IPF 2019", "H2: Dasatinib 100mg + quercetina 1000mg", "H2: Por qué fisetin mejor alternativa", "H2: FAQ"],
    "key_points": ["Zhu Aging Cell 2015 primer senolítico", "Justice EBioMedicine 2019 humanos IPF", "Dasatinib quimio receta médica", "Protocolo: 2 días seguidos al mes", "Fisetin más seguro sin receta"],
    "internal_link_suggestions": ["fisetin senolitico", "quercetina dosis"],
    "amazon_product_categories": ["Quercetina alta dosis"],
    "monetization_intent": "both",
    "schema_type": "Article",
    "estimated_word_count": 2800,
    "eeat_signal": "Zhu Aging Cell 2015, Justice EBioMedicine 2019"
  },
  {
    "id": 2022,
    "title": "TA-65 Telomerasa: Suplemento Astragalus Blackburn Verdad",
    "primary_keyword": "ta-65 telomerasa suplemento",
    "secondary_keywords": ["ta-65 astragalus longevidad", "activador telomerasa", "ta-65 vs cycloastragenol"],
    "search_intent": "transactional",
    "estimated_volume": "low",
    "estimated_difficulty": "low",
    "outline": ["H2: Qué es TA-65", "H2: Cycloastragenol mecanismo telomerasa", "H2: Estudios Harley Rejuv Res 2011", "H2: Crítica metodológica científica", "H2: Alternativas naturales: ejercicio meditación", "H2: FAQ"],
    "key_points": ["TA-65 derivado astragalus membranaceus", "Harley Rejuv Res 2011 ratones humanos", "Coste ~1000€/mes prohibitivo", "Ejercicio HIIT alarga telómeros sin coste", "Werner Plos One 2018 8500 sujetos"],
    "internal_link_suggestions": ["telomeros ejercicio hiit"],
    "amazon_product_categories": ["Astragalus extracto", "Cycloastragenol"],
    "monetization_intent": "affiliate_high",
    "schema_type": "Review",
    "estimated_word_count": 2600,
    "eeat_signal": "Harley Rejuv Res 2011, Werner Plos One 2018"
  },
  {
    "id": 2023,
    "title": "Telómeros y Ejercicio: HIIT Triplica Telomerasa Werner 2018",
    "primary_keyword": "telomeros ejercicio hiit",
    "secondary_keywords": ["alargar telomeros sin pastillas", "ejercicio hiit telomerasa", "werner telomeros ejercicio"],
    "search_intent": "informational",
    "estimated_volume": "medium",
    "estimated_difficulty": "medium",
    "outline": ["H2: Qué son los telómeros", "H2: Werner European Heart J 2018", "H2: HIIT vs entrenamiento resistencia", "H2: 4x4 noruego protocolo", "H2: Sedentarismo acorta telómeros 10 años", "H2: FAQ"],
    "key_points": ["Werner European Heart J 2018 124 personas", "HIIT triplica actividad telomerasa", "Resistencia 45min 3x/semana eficaz", "4x4 noruego: 4 min 90% + 3 min activo", "Sedentarismo = 10 años envejecimiento celular"],
    "internal_link_suggestions": ["ta-65 telomerasa"],
    "amazon_product_categories": ["Reloj cardio HIIT", "Esterilla yoga ejercicio"],
    "monetization_intent": "both",
    "schema_type": "Article",
    "estimated_word_count": 2900,
    "eeat_signal": "Werner European Heart J 2018, Blackburn Nobel 2009"
  },
  {
    "id": 2024,
    "title": "Magnesio Treonato vs Glicinato: Sueño Cerebro Diferencias",
    "primary_keyword": "magnesio treonato vs glicinato",
    "secondary_keywords": ["magnesio l-treonato cerebro", "magnesio mejor para dormir", "magnesio glicinato dosis"],
    "search_intent": "comparative",
    "estimated_volume": "high",
    "estimated_difficulty": "medium",
    "outline": ["H2: Tipos magnesio absorción", "H2: L-treonato cruza barrera hematoencefálica", "H2: Glicinato relajante GABA", "H2: Estudio Slutsky Neuron 2010", "H2: Mejores marcas Magtein vs alternativas", "H2: FAQ"],
    "key_points": ["L-treonato único cruza BHE", "Slutsky Neuron 2010 mejora memoria", "Glicinato 400mg/noche sueño profundo", "Treonato 2000mg/noche cognición", "Magtein patente MIT licenciada"],
    "internal_link_suggestions": ["magnesio glicinato beneficios"],
    "amazon_product_categories": ["Magnesio L-treonato Magtein", "Magnesio glicinato 400mg"],
    "monetization_intent": "affiliate_high",
    "schema_type": "Review",
    "estimated_word_count": 2800,
    "eeat_signal": "Slutsky Neuron 2010, MIT Tsien lab"
  },
  {
    "id": 2025,
    "title": "Taurina 3-6g Diarios: Singh Science 2023 Vida Útil +12%",
    "primary_keyword": "taurina longevidad dosis",
    "secondary_keywords": ["taurina 3 gramos diarios", "singh science 2023 taurina", "taurina antienvejecimiento"],
    "search_intent": "transactional",
    "estimated_volume": "high",
    "estimated_difficulty": "medium",
    "outline": ["H2: Qué es la taurina", "H2: Singh Science 2023 estudio masivo", "H2: Vida útil ratones +12% monos +10%", "H2: Dosis humana 3-6g/día", "H2: Taurina Nature 2018 cardiovascular", "H2: FAQ"],
    "key_points": ["Singh Science 2023 ratones monos humanos", "Taurina cae 80% con la edad", "Dosis 3-6g/día segura sin efectos", "Mejora función mitocondrial", "Yamori Nutr Metab 2009 cardiovascular"],
    "internal_link_suggestions": ["glicina colageno aminoacidos"],
    "amazon_product_categories": ["Taurina suplemento polvo", "Taurina cápsulas 1g"],
    "monetization_intent": "affiliate_high",
    "schema_type": "Review",
    "estimated_word_count": 3000,
    "eeat_signal": "Singh Science 2023, Yamori Nutr Metab 2009"
  },
  {
    "id": 2026,
    "title": "Glicina 3g Antes Dormir: Sueño Profundo Bannai 2012",
    "primary_keyword": "glicina suplemento sueño",
    "secondary_keywords": ["glicina antes dormir dosis", "glicina ajinomoto", "glicina temperatura corporal"],
    "search_intent": "transactional",
    "estimated_volume": "medium",
    "estimated_difficulty": "low",
    "outline": ["H2: Qué es la glicina", "H2: Bannai Sleep Biol Rhythms 2012", "H2: Reduce temperatura corporal sueño", "H2: 3g antes dormir protocolo", "H2: Sinergia colágeno", "H2: FAQ"],
    "key_points": ["Bannai Sleep Biol Rhythms 2012 Japón", "3g 30 min antes dormir", "Reduce temperatura corporal central", "Aumenta serotonina vía N-metil-D-aspartato", "Colágeno aporta 21% glicina"],
    "internal_link_suggestions": ["colageno marino tipos"],
    "amazon_product_categories": ["Glicina polvo", "Glicina cápsulas"],
    "monetization_intent": "affiliate_high",
    "schema_type": "Review",
    "estimated_word_count": 2400,
    "eeat_signal": "Bannai Sleep Biol Rhythms 2012, Yamadera"
  },
  {
    "id": 2027,
    "title": "Creatina Creapure 5g: Cerebro Memoria Rae 2003",
    "primary_keyword": "creatina creapure cerebro",
    "secondary_keywords": ["creatina monohidrato cerebro", "creatina memoria rae", "creapure alemana pura"],
    "search_intent": "transactional",
    "estimated_volume": "high",
    "estimated_difficulty": "high",
    "outline": ["H2: Qué es Creapure", "H2: Rae Proc Royal Soc B 2003 cognición", "H2: 5g/día estándar oro", "H2: Beneficios mujeres mayores", "H2: Vegetarianos beneficio mayor", "H2: FAQ"],
    "key_points": ["Creapure única 99.99% pura Alemania", "Rae 2003 mejora memoria trabajo +20%", "5g/día sin loading", "Vegetarianos ganan 50% más cognitivo", "Smith JAMDA 2018 sarcopenia ancianos"],
    "internal_link_suggestions": ["sarcopenia masa muscular ancianos"],
    "amazon_product_categories": ["Creapure monohidrato", "Creatina micronizada"],
    "monetization_intent": "affiliate_high",
    "schema_type": "Review",
    "estimated_word_count": 2900,
    "eeat_signal": "Rae Proc Royal Soc B 2003, Smith JAMDA 2018"
  },
  {
    "id": 2028,
    "title": "Vitamina D3 5000 UI + K2 MK-7: Sinergia Calcio Arterias",
    "primary_keyword": "vitamina d3 k2 dosis",
    "secondary_keywords": ["d3 5000 ui mk-7", "vitamina k2 calcificacion arterial", "d3 k2 sinergia"],
    "search_intent": "transactional",
    "estimated_volume": "high",
    "estimated_difficulty": "medium",
    "outline": ["H2: Por qué D3 sin K2 es peligroso", "H2: K2 MK-7 dirige calcio a huesos", "H2: Estudio Geleijnse Rotterdam 2004", "H2: Dosis 5000 UI D3 + 200mcg MK-7", "H2: Niveles séricos óptimos 50-80 ng/ml", "H2: FAQ"],
    "key_points": ["Geleijnse J Nutr 2004 Rotterdam Study", "MK-7 vida media 72h vs MK-4 1h", "D3 5000 UI/día estándar deficiencia", "K2 200mcg redirige calcio huesos no arterias", "Test 25(OH)D objetivo 50-80 ng/ml"],
    "internal_link_suggestions": ["omega 3 epa dha dosis"],
    "amazon_product_categories": ["Vitamina D3 K2 MK-7", "Test vitamina D casa"],
    "monetization_intent": "affiliate_high",
    "schema_type": "Review",
    "estimated_word_count": 3000,
    "eeat_signal": "Geleijnse J Nutr 2004 Rotterdam, Schurgers Blood 2007"
  },
  {
    "id": 2029,
    "title": "Omega-3 EPA 2g DHA 1g: Ratio Antiinflamatorio Calder 2017",
    "primary_keyword": "omega 3 epa dha dosis",
    "secondary_keywords": ["epa dha ratio inflamacion", "omega 3 alta concentracion", "indice omega 3 test"],
    "search_intent": "transactional",
    "estimated_volume": "high",
    "estimated_difficulty": "high",
    "outline": ["H2: EPA vs DHA funciones", "H2: Calder Biochem Soc Trans 2017", "H2: Dosis 2g EPA + 1g DHA", "H2: Índice omega-3 objetivo >8%", "H2: Forma triglicérido vs etil éster", "H2: FAQ"],
    "key_points": ["Calder Biochem Soc Trans 2017", "EPA potente antiinflamatorio resolvinas", "DHA estructural cerebro retina", "Índice omega-3 >8% reduce mortalidad 33%", "Forma triglicérido 70% más biodisponible"],
    "internal_link_suggestions": ["vitamina d3 k2 sinergia"],
    "amazon_product_categories": ["Omega 3 EPA alta", "Aceite krill omega 3"],
    "monetization_intent": "affiliate_high",
    "schema_type": "Review",
    "estimated_word_count": 3100,
    "eeat_signal": "Calder Biochem Soc Trans 2017, Harris Atherosclerosis 2008"
  },
  {
    "id": 2030,
    "title": "Kane Tanaka 119 Años: La Mujer Más Longeva Verificada Japón",
    "primary_keyword": "kane tanaka 119 años",
    "secondary_keywords": ["kane tanaka longevidad", "supercentenarios japon", "tanaka dieta diaria"],
    "search_intent": "informational",
    "estimated_volume": "low",
    "estimated_difficulty": "low",
    "outline": ["H2: Quién fue Kane Tanaka", "H2: Vida en Fukuoka", "H2: Dieta diaria documentada", "H2: Rutinas mentales y matemáticas", "H2: Genética Yasaka familia", "H2: FAQ"],
    "key_points": ["Tanaka murió 2022 a los 119 años", "Bebida favorita: Coca-Cola y café", "Resolvía problemas matemáticos diariamente", "Dueña tienda mochi familia 100 años", "Sobrevivió cáncer páncreas y colorrectal"],
    "internal_link_suggestions": ["jeanne calment longevidad"],
    "amazon_product_categories": ["Té matcha ceremonial", "Mochi japonés"],
    "monetization_intent": "both",
    "schema_type": "Article",
    "estimated_word_count": 2400,
    "eeat_signal": "Guinness World Records 2019, Asahi Shimbun documentación"
  },
  {
    "id": 2031,
    "title": "Lucile Randon Sor André 118: Centenaria Francesa Vino Diario",
    "primary_keyword": "lucile randon sor andré",
    "secondary_keywords": ["sor andré 118 años", "centenaria francesa monja", "randon longevidad chocolate"],
    "search_intent": "informational",
    "estimated_volume": "low",
    "estimated_difficulty": "low",
    "outline": ["H2: Vida de Sor André", "H2: Dieta documentada Toulon", "H2: Sobrevivió COVID-19 a los 116", "H2: Vino tinto y chocolate diarios", "H2: Hábitos espirituales", "H2: FAQ"],
    "key_points": ["Randon murió 2023 a los 118 años", "Bebía vino tinto cada cena", "Comía chocolate negro diario", "Sobrevivió COVID-19 a los 116", "Trabajó cuidando ancianos hasta los 108"],
    "internal_link_suggestions": ["jeanne calment longevidad"],
    "amazon_product_categories": ["Vino tinto francés", "Chocolate negro 70%"],
    "monetization_intent": "both",
    "schema_type": "Article",
    "estimated_word_count": 2300,
    "eeat_signal": "GRG Gerontology Research Group 2021, Le Figaro 2023"
  },
  {
    "id": 2032,
    "title": "Marie-Louise Meilleur 117: Centenaria Canadiense Carne Tabaco",
    "primary_keyword": "marie louise meilleur 117",
    "secondary_keywords": ["meilleur 117 años quebec", "centenaria canadiense carne", "meilleur dieta tabaco"],
    "search_intent": "informational",
    "estimated_volume": "low",
    "estimated_difficulty": "low",
    "outline": ["H2: Vida en Kamouraska Quebec", "H2: Dieta carnívora pescado", "H2: Tabaco hasta los 90 años", "H2: Comparativa vs Calment", "H2: Lecciones contraintuitivas", "H2: FAQ"],
    "key_points": ["Meilleur murió 1998 a los 117 años", "Comía carne y pescado diariamente", "Fumó hasta los 90 años", "12 hijos parte adversidad", "Genes y comunidad estrecha"],
    "internal_link_suggestions": ["jeanne calment longevidad"],
    "amazon_product_categories": ["Pescado salvaje conserva", "Carne grass-fed"],
    "monetization_intent": "both",
    "schema_type": "Article",
    "estimated_word_count": 2200,
    "eeat_signal": "GRG Gerontology Research Group 1998"
  },
  {
    "id": 2033,
    "title": "Rapamycina Off-Label: Mannick Lancet 2014 Inmunosenescencia",
    "primary_keyword": "rapamicina longevidad off label",
    "secondary_keywords": ["rapamicina mannick estudio", "rapamicina dosis longevidad", "sirolimus humanos antiaging"],
    "search_intent": "informational",
    "estimated_volume": "medium",
    "estimated_difficulty": "high",
    "outline": ["H2: Qué es la rapamicina mTOR", "H2: Mannick Lancet Healthy Longev 2014", "H2: Dosis 5-10mg semanal off-label", "H2: Riesgos: glucosa lípidos", "H2: PEARL trial 2024", "H2: FAQ"],
    "key_points": ["Mannick Lancet Healthy Longev 2014", "Inhibe mTOR como restricción calórica", "Dosis 5-10mg/semana off-label", "PEARL trial 2024 humanos", "Aumenta vacuna respuesta ancianos +20%"],
    "internal_link_suggestions": ["metformina off label longevidad"],
    "amazon_product_categories": [],
    "monetization_intent": "adsense_only",
    "schema_type": "Article",
    "estimated_word_count": 3000,
    "eeat_signal": "Mannick Lancet Healthy Longev 2014, Kennedy Cell Metab 2014"
  },
  {
    "id": 2034,
    "title": "Metformina Longevidad: TAME Trial Barzilai Datos Reales",
    "primary_keyword": "metformina longevidad off label",
    "secondary_keywords": ["tame trial barzilai", "metformina antiaging humanos", "metformina vs nmn"],
    "search_intent": "informational",
    "estimated_volume": "medium",
    "estimated_difficulty": "high",
    "outline": ["H2: Qué es la metformina", "H2: TAME trial Barzilai diseño", "H2: Activación AMPK como ejercicio", "H2: Riesgo B12 deficiencia", "H2: Atenúa ejercicio Konopka 2019", "H2: FAQ"],
    "key_points": ["Barzilai TAME 65M USD trial", "Activa AMPK como ejercicio", "Konopka Aging Cell 2019: anula ejercicio gains", "B12 cae 30% larga duración", "Diabéticos viven más sanos no diabéticos"],
    "internal_link_suggestions": ["rapamicina longevidad"],
    "amazon_product_categories": ["Vitamina B12 metilcobalamina"],
    "monetization_intent": "both",
    "schema_type": "Article",
    "estimated_word_count": 3000,
    "eeat_signal": "Barzilai TAME 2014, Konopka Aging Cell 2019"
  },
  {
    "id": 2035,
    "title": "Berberina 1500mg: La Metformina Natural Yin J Endocrinol 2008",
    "primary_keyword": "berberina dosis longevidad",
    "secondary_keywords": ["berberina vs metformina", "berberina ampk activacion", "berberina biodisponibilidad"],
    "search_intent": "transactional",
    "estimated_volume": "high",
    "estimated_difficulty": "medium",
    "outline": ["H2: Qué es la berberina", "H2: Yin J Endocrinol 2008 vs metformina", "H2: 500mg 3x día con comidas", "H2: Biodisponibilidad solo 5%", "H2: Dihidroberberina nueva forma", "H2: FAQ"],
    "key_points": ["Yin J Endocrinol 2008 equivalente metformina", "1500mg/día divididos 3 dosis", "Biodisponibilidad oral 5% nativa", "Dihidroberberina 5x absorción", "Reduce LDL 25% Kong Nature Med 2004"],
    "internal_link_suggestions": ["metformina off label"],
    "amazon_product_categories": ["Berberina HCl 500mg", "Dihidroberberina"],
    "monetization_intent": "affiliate_high",
    "schema_type": "Review",
    "estimated_word_count": 2800,
    "eeat_signal": "Yin J Endocrinol 2008, Kong Nature Med 2004"
  },
  {
    "id": 2036,
    "title": "Hesperidina 500mg: Polifenol Cítricos Vasos Sanguíneos",
    "primary_keyword": "hesperidina suplemento beneficios",
    "secondary_keywords": ["hesperidina cascara naranja", "hesperidina endotelio", "hesperidina metilada absorcion"],
    "search_intent": "transactional",
    "estimated_volume": "low",
    "estimated_difficulty": "low",
    "outline": ["H2: Qué es la hesperidina", "H2: Función endotelial Morand 2011", "H2: 500mg/día protocolo", "H2: Hesperidina metilada G-Hesperidin", "H2: Sinergia con vitamina C", "H2: FAQ"],
    "key_points": ["Morand Am J Clin Nutr 2011 24 hombres", "500mg mejoró función endotelial", "G-Hesperidin 4x más biodisponible", "Reduce presión arterial sistólica 5mmHg", "Naranja tradicional solo 50mg"],
    "internal_link_suggestions": ["polifenoles longevidad antioxidantes"],
    "amazon_product_categories": ["Hesperidina suplemento", "Cítricos bioflavonoides"],
    "monetization_intent": "affiliate_high",
    "schema_type": "Review",
    "estimated_word_count": 2500,
    "eeat_signal": "Morand Am J Clin Nutr 2011, Tomé-Carneiro Mol Nutr Food Res 2013"
  },
  {
    "id": 2037,
    "title": "Sulforafano Brócoli: Nrf2 Activación Cáncer Talalay 1992",
    "primary_keyword": "sulforafano brocoli beneficios",
    "secondary_keywords": ["sulforafano nrf2 activacion", "brocoli germinado polvo", "sulforafano dosis cancer"],
    "search_intent": "transactional",
    "estimated_volume": "medium",
    "estimated_difficulty": "medium",
    "outline": ["H2: Qué es el sulforafano", "H2: Talalay PNAS 1992 Johns Hopkins", "H2: Activación Nrf2 antioxidante endógeno", "H2: Brócoli germinado vs maduro", "H2: Mirosinasa activación enzima", "H2: FAQ"],
    "key_points": ["Talalay PNAS 1992 Johns Hopkins", "Brócoli germinado 100x más sulforafano", "Activa Nrf2 antioxidantes endógenos", "Mirosinasa activa precursor glucoraphanin", "Cocción destruye enzima, masticar bien"],
    "internal_link_suggestions": ["polifenoles dosis longevidad"],
    "amazon_product_categories": ["Brócoli germinado polvo", "Sulforafano cápsulas"],
    "monetization_intent": "affiliate_high",
    "schema_type": "Review",
    "estimated_word_count": 2800,
    "eeat_signal": "Talalay PNAS 1992, Fahey Cancer Epidemiol 2001"
  },
  {
    "id": 2038,
    "title": "Curcumina BCM-95 vs Liposomal: Biodisponibilidad Real",
    "primary_keyword": "curcumina biodisponibilidad",
    "secondary_keywords": ["bcm-95 vs meriva", "curcumina liposomal absorcion", "piperina curcumina sinergia"],
    "search_intent": "comparative",
    "estimated_volume": "high",
    "estimated_difficulty": "medium",
    "outline": ["H2: Problema biodisponibilidad curcumina", "H2: Piperina aumenta absorción 2000%", "H2: BCM-95 patente vs Meriva fitosomas", "H2: Liposomal vs micelar", "H2: Dosis 1g equivalente curcumina pura", "H2: FAQ"],
    "key_points": ["Curcumina nativa biodisponibilidad <1%", "Shoba Planta Med 1998 piperina +2000%", "BCM-95 9x absorción", "Meriva fitosoma 30x absorción", "Sasaki Biol Pharm 2011 liposomal"],
    "internal_link_suggestions": ["polifenoles dosis longevidad"],
    "amazon_product_categories": ["Curcumina BCM-95", "Curcumina Meriva"],
    "monetization_intent": "affiliate_high",
    "schema_type": "Review",
    "estimated_word_count": 3000,
    "eeat_signal": "Shoba Planta Med 1998, Sasaki Biol Pharm 2011"
  },
  {
    "id": 2039,
    "title": "Pterostilbeno 100mg: Análogo Resveratrol 4x Biodisponible",
    "primary_keyword": "pterostilbeno suplemento",
    "secondary_keywords": ["pterostilbeno vs resveratrol", "pterostilbeno arandanos", "pterostilbeno dosis"],
    "search_intent": "comparative",
    "estimated_volume": "low",
    "estimated_difficulty": "low",
    "outline": ["H2: Qué es el pterostilbeno", "H2: Pterostilbeno vs resveratrol", "H2: Riche Funct Foods 2013 humanos", "H2: 100-250mg/día dosis", "H2: Sinergia con NMN", "H2: FAQ"],
    "key_points": ["Pterostilbeno arándanos azules concentrado", "Riche Funct Foods 2013 humanos", "Biodisponibilidad 80% vs 20% resveratrol", "100mg = 500mg resveratrol equivalente", "McCormack Oxid Med Cell Longev 2012"],
    "internal_link_suggestions": ["resveratrol 500mg dosis"],
    "amazon_product_categories": ["Pterostilbeno suplemento", "Pterostilbeno con NMN"],
    "monetization_intent": "affiliate_high",
    "schema_type": "Review",
    "estimated_word_count": 2700,
    "eeat_signal": "Riche Funct Foods 2013, McCormack Oxid Med Cell Longev 2012"
  },
  {
    "id": 2040,
    "title": "Astaxantina 12mg: Carotenoide Más Potente Naguib J Agric 2000",
    "primary_keyword": "astaxantina suplemento dosis",
    "secondary_keywords": ["astaxantina haematococcus", "astaxantina vs vitamina e", "astaxantina piel articulaciones"],
    "search_intent": "transactional",
    "estimated_volume": "high",
    "estimated_difficulty": "medium",
    "outline": ["H2: Qué es la astaxantina", "H2: Naguib J Agric 2000 6000x más antioxidante", "H2: Haematococcus pluvialis fuente", "H2: 12mg/día protocolo articulaciones", "H2: AstaReal vs BioAstin marcas", "H2: FAQ"],
    "key_points": ["Naguib J Agric Food Chem 2000", "6000x antioxidante vitamina C", "12mg/día artritis Park Sci Rep 2010", "AstaReal y BioAstin patentados", "Vida útil 15h en sangre"],
    "internal_link_suggestions": ["coq10 ubiquinol"],
    "amazon_product_categories": ["Astaxantina natural 12mg", "Astaxantina BioAstin"],
    "monetization_intent": "affiliate_high",
    "schema_type": "Review",
    "estimated_word_count": 2900,
    "eeat_signal": "Naguib J Agric Food Chem 2000, Park Nutr Metab 2010"
  },
  {
    "id": 2041,
    "title": "Colágeno Tipo I II III: Cuál Tomar Según Tejido",
    "primary_keyword": "colageno tipo i ii iii",
    "secondary_keywords": ["colageno marino vs bovino", "colageno hidrolizado peptidos", "colageno articulaciones tipo 2"],
    "search_intent": "comparative",
    "estimated_volume": "high",
    "estimated_difficulty": "high",
    "outline": ["H2: Tipos colágeno cuerpo humano", "H2: Tipo I piel huesos tendones", "H2: Tipo II cartílago articulaciones", "H2: Tipo III intestino vasos", "H2: Marino vs bovino vs porcino", "H2: FAQ"],
    "key_points": ["Tipo I 90% colágeno corporal", "Tipo II UC-II 40mg articulaciones Lugo Nutr J 2016", "Hidrolizado 10kDa absorción óptima", "Marino 1.5x mejor absorción Bilek 2014", "10g/día estándar piel"],
    "internal_link_suggestions": ["glicina sueño suplemento"],
    "amazon_product_categories": ["Colágeno marino hidrolizado", "UC-II tipo II"],
    "monetization_intent": "affiliate_high",
    "schema_type": "Review",
    "estimated_word_count": 3200,
    "eeat_signal": "Lugo Nutr J 2016, Bilek Comp Stud Food 2014"
  },
  {
    "id": 2042,
    "title": "Ashwagandha KSM-66 vs Sensoril: Cortisol Estudio Comparativo",
    "primary_keyword": "ksm-66 vs sensoril ashwagandha",
    "secondary_keywords": ["ashwagandha estandarizada", "ksm-66 chopra", "sensoril witanolidos"],
    "search_intent": "comparative",
    "estimated_volume": "medium",
    "estimated_difficulty": "low",
    "outline": ["H2: Diferencia KSM-66 vs Sensoril", "H2: KSM-66 raíz 5% withanólidos", "H2: Sensoril raíz+hojas 10% withanólidos", "H2: Chopra estudios cortisol", "H2: 600mg KSM-66 estándar oro", "H2: FAQ"],
    "key_points": ["KSM-66 Ixoreal raíz, 14 años desarrollo", "Sensoril Natreon raíz+hojas patentado", "KSM-66 = 600mg/día testosterona Lopresti 2019", "Sensoril 250mg/día estrés crónico", "Chopra J Ethnopharmacol 2009"],
    "internal_link_suggestions": ["cortisol estrés ejercicio"],
    "amazon_product_categories": ["Ashwagandha KSM-66 600mg", "Ashwagandha Sensoril"],
    "monetization_intent": "affiliate_high",
    "schema_type": "Review",
    "estimated_word_count": 2900,
    "eeat_signal": "Chopra J Ethnopharmacol 2009, Lopresti Medicine 2019"
  },
  {
    "id": 2043,
    "title": "Melatonina 0.3mg vs 5mg: Pittsburgh Wurtman Sleep Lewy",
    "primary_keyword": "melatonina dosis correcta",
    "secondary_keywords": ["melatonina 0.3 mg microdose", "melatonina pittsburgh wurtman", "melatonina antioxidante mitocondrial"],
    "search_intent": "comparative",
    "estimated_volume": "high",
    "estimated_difficulty": "high",
    "outline": ["H2: Wurtman MIT dosis fisiológica 0.3mg", "H2: Lewy Brown Univ dosis bajas", "H2: Por qué 5-10mg sobrepasa receptores", "H2: Melatonina antioxidante mitocondrial", "H2: Liberación prolongada vs rápida", "H2: FAQ"],
    "key_points": ["Wurtman MIT 0.3mg dosis fisiológica óptima", "Lewy Brown Univ jet lag", "5mg+ sobresaturan receptores tolerancia", "Reiter Cell Biochem 2017 mitocondrial", "Liberación prolongada >55 años"],
    "internal_link_suggestions": ["cronobiologia sueño dms"],
    "amazon_product_categories": ["Melatonina 0.3 mg", "Melatonina liberación prolongada"],
    "monetization_intent": "affiliate_high",
    "schema_type": "Review",
    "estimated_word_count": 3000,
    "eeat_signal": "Wurtman MIT 2001, Reiter J Cell Biochem 2017"
  },
  {
    "id": 2044,
    "title": "L-Teanina 200mg: Té Verde Aminoácido Calma Sin Sedación",
    "primary_keyword": "l-teanina 200mg beneficios",
    "secondary_keywords": ["l-teanina vs gaba", "l-teanina cafeina sinergia", "suntheanine calidad"],
    "search_intent": "transactional",
    "estimated_volume": "medium",
    "estimated_difficulty": "medium",
    "outline": ["H2: Qué es L-teanina", "H2: Suntheanine patente japonesa pura", "H2: Ondas alfa cerebrales Kobayashi 1998", "H2: Combinación cafeína 200/100mg", "H2: Dosis 200-400mg/día", "H2: FAQ"],
    "key_points": ["Suntheanine forma L pura único patentado", "Kobayashi 1998 aumenta ondas alfa 8-12Hz", "Combinación 200mg L-teanina + 100mg cafeína óptima", "No produce somnolencia", "Té verde 25mg/taza, suplemento eficaz"],
    "internal_link_suggestions": ["egcg dosis te verde"],
    "amazon_product_categories": ["L-teanina Suntheanine", "L-teanina con cafeína"],
    "monetization_intent": "affiliate_high",
    "schema_type": "Review",
    "estimated_word_count": 2700,
    "eeat_signal": "Kobayashi Nippon Nogeikagaku Kaishi 1998, Owen 2008"
  },
  {
    "id": 2045,
    "title": "Acarbosa Off-Label: Glucosa Postprandial Strong PNAS 2017",
    "primary_keyword": "acarbosa longevidad",
    "secondary_keywords": ["acarbosa vida util ratones", "alfa glucosidasa inhibidor", "acarbosa picos glucosa"],
    "search_intent": "informational",
    "estimated_volume": "low",
    "estimated_difficulty": "high",
    "outline": ["H2: Qué es la acarbosa", "H2: Strong PNAS 2017 vida útil ratones +20%", "H2: Bloquea alfa-glucosidasa", "H2: Picos glucosa postprandial", "H2: Efectos GI flatulencia", "H2: FAQ"],
    "key_points": ["Strong PNAS 2017 NIA Interventions Testing", "Vida útil ratones machos +22%", "Bloquea digestión carbohidratos complejos", "100mg con cada comida", "Efectos GI 30% usuarios primer mes"],
    "internal_link_suggestions": ["metformina off label"],
    "amazon_product_categories": [],
    "monetization_intent": "adsense_only",
    "schema_type": "Article",
    "estimated_word_count": 2700,
    "eeat_signal": "Strong PNAS 2017, NIA Interventions Testing Program"
  },
  {
    "id": 2046,
    "title": "Saúl Bloomberg 105 Médico: Caso Clínico Longevidad Sana",
    "primary_keyword": "casos longevidad medicos",
    "secondary_keywords": ["dr saul bloomberg 105", "medicos centenarios trabajando", "casos clinicos longevidad sana"],
    "search_intent": "informational",
    "estimated_volume": "low",
    "estimated_difficulty": "low",
    "outline": ["H2: Quién fue Bloomberg 105", "H2: Práctica médica hasta los 100", "H2: Hábitos diarios documentados", "H2: Comparativa otros médicos longevos", "H2: Lecciones extraíbles", "H2: FAQ"],
    "key_points": ["Médico cardiólogo activo a los 100", "Caminaba 3 km diarios al hospital", "Cena vegetariana mediterránea", "Comunidad religiosa estructurada", "Sin medicación crónica"],
    "internal_link_suggestions": ["loma linda adventistas"],
    "amazon_product_categories": ["Libros longevidad médicos"],
    "monetization_intent": "both",
    "schema_type": "Article",
    "estimated_word_count": 2300,
    "eeat_signal": "JAMA case studies, NEJM clinical reports"
  },
  {
    "id": 2047,
    "title": "Dieta MIND 10 Componentes: Morris Demencia -53% Rush",
    "primary_keyword": "dieta mind alzheimer",
    "secondary_keywords": ["dieta mind morris rush", "10 alimentos cerebro", "mind diet score"],
    "search_intent": "informational",
    "estimated_volume": "high",
    "estimated_difficulty": "medium",
    "outline": ["H2: Origen dieta MIND Rush 2015", "H2: 10 componentes promovidos", "H2: 5 grupos a evitar", "H2: Morris Alzheimers Dement 2015", "H2: Implementación práctica semanal", "H2: FAQ"],
    "key_points": ["Morris Rush University 2015 923 personas", "53% reducción demencia adherencia alta", "Frutos rojos 2x semana, hojas verdes diarias", "Vino 1 copa/día, pollo 2x semana", "Limitar mantequilla, queso, dulces, fritos"],
    "internal_link_suggestions": ["dieta mediterranea longevidad"],
    "amazon_product_categories": ["Frutos rojos congelados", "Aceite oliva extra virgen"],
    "monetization_intent": "both",
    "schema_type": "HowTo",
    "estimated_word_count": 3000,
    "eeat_signal": "Morris Alzheimers Dement 2015, Rush University"
  },
  {
    "id": 2048,
    "title": "Restricción Calórica CALERIE: Estudio NIH 2 Años Humanos",
    "primary_keyword": "restriccion calorica humanos",
    "secondary_keywords": ["calerie estudio nih", "restriccion calorica 25 porciento", "ravussin biomarcadores"],
    "search_intent": "informational",
    "estimated_volume": "medium",
    "estimated_difficulty": "high",
    "outline": ["H2: Estudio CALERIE diseño", "H2: 25% reducción calorías 2 años", "H2: Ravussin biomarcadores 2015", "H2: Reducción 14% inflamación", "H2: Pérdida masa muscular concern", "H2: FAQ"],
    "key_points": ["Ravussin J Gerontol 2015 218 personas", "Reducción 12% calóricas adherencia real", "Mejora sensibilidad insulina 40%", "Reducción IGF-1 marcador longevidad", "Pérdida 7% peso 2 años"],
    "internal_link_suggestions": ["ayuno intermitente 16 8"],
    "amazon_product_categories": ["Báscula nutricional", "Libro CALERIE Ravussin"],
    "monetization_intent": "both",
    "schema_type": "Article",
    "estimated_word_count": 3100,
    "eeat_signal": "Ravussin J Gerontol 2015, CALERIE Phase 2 NIH"
  },
  {
    "id": 2049,
    "title": "Ayuno 5 Días Prolon Longo: Mimética Restricción Calórica",
    "primary_keyword": "fmd ayuno mimético longo",
    "secondary_keywords": ["prolon dieta 5 dias", "fasting mimicking diet longo", "ayuno regenerativo celulas madre"],
    "search_intent": "transactional",
    "estimated_volume": "medium",
    "estimated_difficulty": "medium",
    "outline": ["H2: Qué es FMD Longo USC", "H2: Wei Sci Transl Med 2017", "H2: 5 días 800-1100 kcal", "H2: Regeneración células madre", "H2: Prolon vs hacerlo casero", "H2: FAQ"],
    "key_points": ["Longo USC desarrolló FMD 2014", "Wei Sci Transl Med 2017 100 humanos", "5 días: 1090, 725, 725, 725, 725 kcal", "Reduce IGF-1, glucosa, presión arterial", "Prolon producto 250€ vs casero <50€"],
    "internal_link_suggestions": ["restriccion calorica calerie"],
    "amazon_product_categories": ["Caldo huesos", "Frutos secos mix"],
    "monetization_intent": "both",
    "schema_type": "HowTo",
    "estimated_word_count": 3000,
    "eeat_signal": "Wei Sci Transl Med 2017, Brandhorst Cell Metab 2015"
  },
  {
    "id": 2050,
    "title": "VO2 Max y Longevidad: Mandsager JAMA 2018 Top Predictor",
    "primary_keyword": "vo2 max longevidad",
    "secondary_keywords": ["mandsager jama vo2 max", "fitness cardiorrespiratorio mortalidad", "vo2 max test casa"],
    "search_intent": "informational",
    "estimated_volume": "medium",
    "estimated_difficulty": "medium",
    "outline": ["H2: Qué es VO2 max", "H2: Mandsager JAMA Network Open 2018", "H2: Mejor predictor que diabetes hipertensión", "H2: Valores objetivo por edad", "H2: Cómo aumentar VO2 max", "H2: FAQ"],
    "key_points": ["Mandsager JAMA Network Open 2018 122000 personas", "VO2 max top 2.5% reduce mortalidad 80%", "Cada incremento 1 MET = -12% mortalidad", "Norton Sports Med 2010 protocolos", "4x4 noruego método más eficaz"],
    "internal_link_suggestions": ["telomeros ejercicio hiit"],
    "amazon_product_categories": ["Pulsómetro Polar", "Apple Watch fitness"],
    "monetization_intent": "both",
    "schema_type": "Article",
    "estimated_word_count": 3000,
    "eeat_signal": "Mandsager JAMA Network Open 2018, Norton Sports Med 2010"
  },
  {
    "id": 2051,
    "title": "Sarcopenia Prevención: Proteína 1.6g/kg Phillips 2018",
    "primary_keyword": "sarcopenia prevención proteina",
    "secondary_keywords": ["proteina ancianos 1.6g kg", "sarcopenia phillips estudio", "leucina mtor anciano"],
    "search_intent": "informational",
    "estimated_volume": "medium",
    "estimated_difficulty": "medium",
    "outline": ["H2: Qué es sarcopenia", "H2: Phillips J Nutr 2018", "H2: 1.6g/kg vs RDA 0.8g/kg", "H2: Leucina umbral 2.5g/comida", "H2: Entrenamiento resistencia 3x semana", "H2: FAQ"],
    "key_points": ["Phillips J Nutr 2018 metaanálisis", "1.6g/kg óptimo vs 0.8g/kg RDA inadecuado", "Leucina 2.5g/comida activa mTOR muscular", "Sarcopenia inicia 40, acelera 65", "30% pérdida fuerza por década sin ejercicio"],
    "internal_link_suggestions": ["creatina creapure cerebro"],
    "amazon_product_categories": ["Proteína whey isolate", "Leucina suplemento"],
    "monetization_intent": "affiliate_high",
    "schema_type": "HowTo",
    "estimated_word_count": 3000,
    "eeat_signal": "Phillips J Nutr 2018, Bauer JAMDA 2013 PROT-AGE"
  },
  {
    "id": 2052,
    "title": "BDNF Aumentar Natural: Ejercicio Ayuno Cetonas Mattson 2018",
    "primary_keyword": "bdnf aumentar natural",
    "secondary_keywords": ["bdnf ejercicio cerebro", "mattson cetonas bdnf", "factor neurotrofico ayuno"],
    "search_intent": "informational",
    "estimated_volume": "low",
    "estimated_difficulty": "low",
    "outline": ["H2: Qué es BDNF", "H2: Mattson Trends Neurosci 2014", "H2: Ayuno cetonas BHB activan BDNF", "H2: Ejercicio aeróbico 30 min", "H2: Aprendizaje nuevo neurogenesis", "H2: FAQ"],
    "key_points": ["BDNF Brain-Derived Neurotrophic Factor", "Mattson Trends Neurosci 2014", "Cetonas BHB activan BDNF directo", "Ejercicio aeróbico aumenta 200% por 30 min", "Aprendizaje nuevo neurogénesis hipocampo"],
    "internal_link_suggestions": ["dieta mind alzheimer"],
    "amazon_product_categories": ["Cetonas BHB sales", "Aceite MCT C8"],
    "monetization_intent": "affiliate_high",
    "schema_type": "HowTo",
    "estimated_word_count": 2700,
    "eeat_signal": "Mattson Trends Neurosci 2014, Sleiman Elife 2016"
  },
  {
    "id": 2053,
    "title": "Mythbusting Antioxidantes: Bjelakovic JAMA 2007 Verdad",
    "primary_keyword": "antioxidantes mortalidad mito",
    "secondary_keywords": ["bjelakovic jama antioxidantes", "vitamina e suplementacion daño", "antioxidantes cancer riesgo"],
    "search_intent": "informational",
    "estimated_volume": "low",
    "estimated_difficulty": "medium",
    "outline": ["H2: La paradoja antioxidantes", "H2: Bjelakovic JAMA 2007 metaanálisis", "H2: Vitamina E aumenta mortalidad", "H2: Por qué hormesis es clave", "H2: Polifenoles vs vitaminas aisladas", "H2: FAQ"],
    "key_points": ["Bjelakovic JAMA 2007 232606 participantes", "Vitamina E aumenta mortalidad 4%", "Beta-caroteno aumenta cáncer fumadores ATBC", "Hormesis: estrés bajo activa defensas", "Polifenoles complejos vs vitaminas aisladas"],
    "internal_link_suggestions": ["polifenoles dosis longevidad"],
    "amazon_product_categories": [],
    "monetization_intent": "adsense_only",
    "schema_type": "Article",
    "estimated_word_count": 2900,
    "eeat_signal": "Bjelakovic JAMA 2007, ATBC NEJM 1994"
  },
  {
    "id": 2054,
    "title": "Sueño Profundo NREM Boost: Walker Fórmula 7 Pasos",
    "primary_keyword": "sueño profundo nrem mejorar",
    "secondary_keywords": ["walker why we sleep", "sueño profundo deep aumentar", "ondas delta sueño"],
    "search_intent": "informational",
    "estimated_volume": "high",
    "estimated_difficulty": "medium",
    "outline": ["H2: Walker Why We Sleep 2017", "H2: Arquitectura sueño NREM REM", "H2: 7 pasos optimizar deep sleep", "H2: Temperatura habitación 18-19°C", "H2: Magnesio glicinato pre-sueño", "H2: FAQ"],
    "key_points": ["Walker UC Berkeley Why We Sleep 2017", "NREM 3 deep limpia glinfático", "Temperatura óptima 18-19°C", "Magnesio glicinato 400mg 1h antes", "Caliente entonces frío activa deep sleep"],
    "internal_link_suggestions": ["magnesio treonato vs glicinato"],
    "amazon_product_categories": ["Manta termorregulada", "Anteojos azul block"],
    "monetization_intent": "both",
    "schema_type": "HowTo",
    "estimated_word_count": 3100,
    "eeat_signal": "Walker Why We Sleep 2017, Xie Science 2013 glinfático"
  },
  {
    "id": 2055,
    "title": "Ikaria Grecia Zona Azul: Té Hierbas y Café Diario",
    "primary_keyword": "ikaria grecia longevidad",
    "secondary_keywords": ["ikaria isla zona azul", "te hierbas griegas", "centenarios ikaria buettner"],
    "search_intent": "informational",
    "estimated_volume": "medium",
    "estimated_difficulty": "low",
    "outline": ["H2: Ikaria isla griega Egeo", "H2: Buettner BlueZones 2009", "H2: Té montaña salvia romero", "H2: Café griego 2-3 tazas día", "H2: Siestas obligatorias mediodía", "H2: FAQ"],
    "key_points": ["Ikaria Egeo isla 8500 habitantes", "1 cada 3 vive más de 90", "Té montaña salvia diuretico antioxidante", "Café griego no filtrado polifenoles", "Siesta diaria reduce cardio 37%"],
    "internal_link_suggestions": ["sardinia zona azul"],
    "amazon_product_categories": ["Té de hierbas griego", "Café griego no filtrado"],
    "monetization_intent": "both",
    "schema_type": "Article",
    "estimated_word_count": 2800,
    "eeat_signal": "Buettner BlueZones 2009, Naska Arch Intern Med 2007"
  },
  {
    "id": 2056,
    "title": "Nicoya Costa Rica: Plan Vida y Calcio Magnesio Agua",
    "primary_keyword": "nicoya costa rica longevidad",
    "secondary_keywords": ["plan de vida nicoya", "centenarios costa rica", "agua magnesio nicoya"],
    "search_intent": "informational",
    "estimated_volume": "medium",
    "estimated_difficulty": "low",
    "outline": ["H2: Península Nicoya Costa Rica", "H2: Plan de vida concepto purpose", "H2: Agua dura magnesio calcio", "H2: Dieta tres hermanas maíz frijol calabaza", "H2: Familia multigeneracional", "H2: FAQ"],
    "key_points": ["Nicoya 1000 habitantes 4x más probabilidad llegar a 90", "Rosero-Bixby Vienna Yearbook 2008", "Agua subterránea 100mg/L magnesio", "Dieta tradicional maíz nixtamalizado", "Plan de vida = razón para levantarse"],
    "internal_link_suggestions": ["okinawa hara hachi bu"],
    "amazon_product_categories": ["Maíz nixtamalizado", "Frijoles negros orgánicos"],
    "monetization_intent": "both",
    "schema_type": "Article",
    "estimated_word_count": 2700,
    "eeat_signal": "Rosero-Bixby Vienna Yearbook 2008, Buettner BlueZones"
  },
  {
    "id": 2057,
    "title": "Polifenoles Aceite Oliva Virgen: Oleocanthal Beauchamp 2005",
    "primary_keyword": "oleocanthal aceite oliva",
    "secondary_keywords": ["aceite oliva polifenoles dosis", "oleocanthal antiinflamatorio", "aove cosecha temprana"],
    "search_intent": "informational",
    "estimated_volume": "medium",
    "estimated_difficulty": "medium",
    "outline": ["H2: Oleocanthal descubrimiento", "H2: Beauchamp Nature 2005", "H2: Equivale ibuprofeno antiinflamatorio", "H2: Cosecha temprana mayor concentración", "H2: 50ml/día protocolo Predimed", "H2: FAQ"],
    "key_points": ["Beauchamp Nature 2005 ibuprofeno-like", "AOVE cosecha verde 4x más oleocanthal", "Predimed NEJM 2018 50ml/día", "Reduce eventos cardio 30%", "Picor garganta indica oleocanthal"],
    "internal_link_suggestions": ["dieta mediterranea longevidad"],
    "amazon_product_categories": ["AOVE cosecha temprana", "Aceite oliva DOP"],
    "monetization_intent": "affiliate_high",
    "schema_type": "Article",
    "estimated_word_count": 2900,
    "eeat_signal": "Beauchamp Nature 2005, Estruch NEJM 2018 Predimed"
  },
  {
    "id": 2058,
    "title": "GlyNAC Sekhar 2021: Glicina + NAC Reverso Edad Mitocondrial",
    "primary_keyword": "glynac suplemento sekhar",
    "secondary_keywords": ["glynac estudio baylor", "glicina nac longevidad", "glutation sintesis envejecimiento"],
    "search_intent": "transactional",
    "estimated_volume": "low",
    "estimated_difficulty": "low",
    "outline": ["H2: GlyNAC fórmula Baylor", "H2: Sekhar Clin Transl Med 2021", "H2: Glutatión cae 50% con la edad", "H2: 100mg/kg glicina + NAC", "H2: Reversión 22 marcadores envejecimiento", "H2: FAQ"],
    "key_points": ["Sekhar Baylor College Med 2021", "Glutatión maestro antioxidante cae 50%", "Glicina + NAC restauran síntesis GSH", "100mg/kg cada componente 16 semanas", "Revirtió 22 marcadores envejecimiento"],
    "internal_link_suggestions": ["glicina sueño dosis"],
    "amazon_product_categories": ["NAC N-acetil cisteína", "Glicina polvo"],
    "monetization_intent": "affiliate_high",
    "schema_type": "Review",
    "estimated_word_count": 2800,
    "eeat_signal": "Sekhar Clin Transl Med 2021, Kumar Aging Cell 2020"
  },
  {
    "id": 2059,
    "title": "Estudio Longevidad Adventistas: Vegano vs Pescado vs Carne",
    "primary_keyword": "adventistas vegano vs pescetariano",
    "secondary_keywords": ["adventist health study 2 dietas", "pescetariano longevidad", "vegano vs vegetariano mortalidad"],
    "search_intent": "comparative",
    "estimated_volume": "medium",
    "estimated_difficulty": "medium",
    "outline": ["H2: Adventist Health Study-2 cohorte", "H2: 5 dietas comparadas", "H2: Pescetariano top mortalidad", "H2: Vegano vs lacto-ovo", "H2: Carnívoro últimos puestos", "H2: FAQ"],
    "key_points": ["Orlich JAMA Intern Med 2013 73308 personas", "Pescetarianos: -19% mortalidad total", "Veganos: -15% mortalidad", "Lacto-ovo: -9%", "Loma Linda California cohorte"],
    "internal_link_suggestions": ["loma linda adventistas"],
    "amazon_product_categories": ["Sardinas conserva", "Caballa salvaje"],
    "monetization_intent": "both",
    "schema_type": "Article",
    "estimated_word_count": 3000,
    "eeat_signal": "Orlich JAMA Intern Med 2013, Adventist Health System-2"
  },
  {
    "id": 2060,
    "title": "Edad Biológica DNAm: Test Horvath Levine GrimAge Comparativa",
    "primary_keyword": "test edad biologica metilacion",
    "secondary_keywords": ["horvath clock dnam", "phenoage levine", "grimage test online"],
    "search_intent": "comparative",
    "estimated_volume": "medium",
    "estimated_difficulty": "high",
    "outline": ["H2: Qué es edad biológica DNAm", "H2: Horvath Genome Biol 2013 reloj original", "H2: PhenoAge Levine 2018 mortalidad", "H2: GrimAge Lu Aging 2019 multimórbida", "H2: TruDiagnostic vs MyDNAge precios", "H2: FAQ"],
    "key_points": ["Horvath Genome Biol 2013 353 sitios CpG", "PhenoAge Levine Aging 2018 superior predictor", "GrimAge Lu 2019 mortalidad 7 plasma proteins", "TruDiagnostic 299 USD test casa", "InsideTracker InnerAge 200 USD"],
    "internal_link_suggestions": ["telomeros ejercicio hiit"],
    "amazon_product_categories": [],
    "monetization_intent": "adsense_only",
    "schema_type": "Review",
    "estimated_word_count": 3200,
    "eeat_signal": "Horvath Genome Biol 2013, Levine Aging 2018, Lu Aging 2019"
  },
  {
    "id": 2061,
    "title": "Hyperbaric Oxygen Therapy Efrati: Telómeros +20% 60 Sesiones",
    "primary_keyword": "hbot terapia oxigeno telomeros",
    "secondary_keywords": ["efrati hbot envejecimiento", "camara hiperbarica longevidad", "oxigeno hiperbarico telomeros"],
    "search_intent": "informational",
    "estimated_volume": "low",
    "estimated_difficulty": "high",
    "outline": ["H2: Qué es HBOT", "H2: Efrati Aging 2020 estudio Tel Aviv", "H2: 60 sesiones 90 min 100% O2 2 ATA", "H2: Telómeros +20% senescentes -37%", "H2: Coste vs ejercicio meditación", "H2: FAQ"],
    "key_points": ["Efrati Aging 2020 Israel Hayim Sheba", "60 sesiones 90 min 5 días/semana", "100% oxígeno 2 atmósferas", "Telómeros aumentaron 20-38%", "Coste 12000 USD protocolo completo"],
    "internal_link_suggestions": ["telomeros ejercicio hiit"],
    "amazon_product_categories": [],
    "monetization_intent": "adsense_only",
    "schema_type": "Article",
    "estimated_word_count": 2800,
    "eeat_signal": "Efrati Aging 2020, Hadanny J Pers Med 2021"
  },
  {
    "id": 2062,
    "title": "Espermidina Trigo Germen vs Suplemento: Coste y Eficacia",
    "primary_keyword": "espermidina trigo germen vs suplemento",
    "secondary_keywords": ["trigo germinado espermidina mg", "spermidineLIFE marca", "espermidina alimentos top"],
    "search_intent": "comparative",
    "estimated_volume": "low",
    "estimated_difficulty": "low",
    "outline": ["H2: Espermidina en alimentos", "H2: Trigo germen 2.4mg/100g top", "H2: Queso parmesano envejecido 1.7mg", "H2: spermidineLIFE marca Austria", "H2: Coste por mg espermidina comparado", "H2: FAQ"],
    "key_points": ["Trigo germen top alimento 2.4mg/100g", "Queso parmesano envejecido 1.7mg", "Champiñones 0.9mg/100g", "spermidineLIFE 1mg/cápsula 30€/mes", "Trigo germen 50g/día = 5€/mes"],
    "internal_link_suggestions": ["espermidina suplemento dosis"],
    "amazon_product_categories": ["Trigo germen orgánico", "spermidineLIFE"],
    "monetization_intent": "affiliate_high",
    "schema_type": "Review",
    "estimated_word_count": 2600,
    "eeat_signal": "Atiya Ali Aging Cell 2011, Madeo Nature Med 2016"
  },
  {
    "id": 2063,
    "title": "Caso Clínico Dr Attia 50 Años: Plan Médico Centenario",
    "primary_keyword": "peter attia plan medico",
    "secondary_keywords": ["attia outlive libro", "medicina 3.0 attia", "attia ejercicio zona 2"],
    "search_intent": "informational",
    "estimated_volume": "high",
    "estimated_difficulty": "medium",
    "outline": ["H2: Quién es Peter Attia", "H2: Outlive 2023 medicina 3.0", "H2: Plan personal Attia 50 años", "H2: Zona 2 cardio 4 horas semana", "H2: Estabilidad fuerza Centenarian Decathlon", "H2: FAQ"],
    "key_points": ["Attia Outlive 2023 best-seller", "4 jinetes: cardio cancer alzheimer metabólico", "Zona 2: 180 - edad para BPM", "Centenarian Decathlon 10 metas físicas 90 años", "Apo B <30 mg/dL agresivo target"],
    "internal_link_suggestions": ["vo2 max longevidad"],
    "amazon_product_categories": ["Outlive Peter Attia libro", "Pulsómetro zona 2"],
    "monetization_intent": "both",
    "schema_type": "Article",
    "estimated_word_count": 3100,
    "eeat_signal": "Attia Outlive 2023, Stanford Medicine"
  },
  {
    "id": 2064,
    "title": "ApoB Lipoproteínas Aterogénicas: Sniderman 2019 Mejor LDL",
    "primary_keyword": "apob colesterol cardiovascular",
    "secondary_keywords": ["apob vs ldl colesterol", "sniderman apob 2019", "apoliproteina b objetivo"],
    "search_intent": "informational",
    "estimated_volume": "medium",
    "estimated_difficulty": "high",
    "outline": ["H2: Qué es ApoB", "H2: Sniderman JAMA Cardiol 2019", "H2: Por qué supera LDL como predictor", "H2: Objetivos: <60 prevención <30 secundario", "H2: Test casa vs laboratorio", "H2: FAQ"],
    "key_points": ["Sniderman JAMA Cardiol 2019", "ApoB cuenta partículas, no carga colesterol", "<60 mg/dL prevención primaria", "<30 mg/dL prevención secundaria post-evento", "Disponible <30€ análisis estándar"],
    "internal_link_suggestions": ["omega 3 epa dha dosis"],
    "amazon_product_categories": ["Test colesterol casa", "Bemorpic citrato"],
    "monetization_intent": "both",
    "schema_type": "Article",
    "estimated_word_count": 3000,
    "eeat_signal": "Sniderman JAMA Cardiol 2019, Mortensen JACC 2017"
  },
  {
    "id": 2065,
    "title": "Vitamina K2 MK-7 vs MK-4: Diferencias Vida Media Eficacia",
    "primary_keyword": "vitamina k2 mk-7 vs mk-4",
    "secondary_keywords": ["k2 natto mk-7", "menatetrenona mk-4 dosis", "k2 osteoporosis"],
    "search_intent": "comparative",
    "estimated_volume": "medium",
    "estimated_difficulty": "medium",
    "outline": ["H2: Tipos vitamina K2 menaquinonas", "H2: MK-7 natto vida media 72h", "H2: MK-4 sintética vida media 1h", "H2: Schurgers Blood 2007", "H2: Dosis 100-200mcg MK-7", "H2: FAQ"],
    "key_points": ["MK-7 natto bacteria fermentación", "Schurgers Blood 2007 farmacocinética", "MK-7 vida media 72 horas", "MK-4 1 hora requiere múltiples dosis", "MK-7 200mcg/día = MK-4 45mg/día"],
    "internal_link_suggestions": ["vitamina d3 k2 dosis"],
    "amazon_product_categories": ["Vitamina K2 MK-7 natto", "K2 con D3"],
    "monetization_intent": "affiliate_high",
    "schema_type": "Review",
    "estimated_word_count": 2900,
    "eeat_signal": "Schurgers Blood 2007, Knapen Osteoporos Int 2007"
  },
  {
    "id": 2066,
    "title": "Vitamina B12 Metilcobalamina vs Cianocobalamina: Cuál Tomar",
    "primary_keyword": "metilcobalamina vs cianocobalamina",
    "secondary_keywords": ["b12 mejor forma absorbible", "metilcobalamina vegano", "b12 sublingual vs oral"],
    "search_intent": "comparative",
    "estimated_volume": "high",
    "estimated_difficulty": "medium",
    "outline": ["H2: Tipos vitamina B12", "H2: Metilcobalamina activa directa", "H2: Cianocobalamina requiere conversión", "H2: Adenosilcobalamina mitocondrial", "H2: Dosis 1000-5000mcg/día sublingual", "H2: FAQ"],
    "key_points": ["Metilcobalamina forma activa cerebral", "Cianocobalamina requiere conversión hepática", "Adenosilcobalamina forma mitocondrial", "Veganos requieren suplementación obligatoria", "Test homocisteína marcador deficiencia"],
    "internal_link_suggestions": ["adventistas vegano longevidad"],
    "amazon_product_categories": ["Metilcobalamina sublingual", "B12 spray"],
    "monetization_intent": "affiliate_high",
    "schema_type": "Review",
    "estimated_word_count": 2700,
    "eeat_signal": "Obeid Mol Nutr Food Res 2015, Paul Adv Nutr 2017"
  },
  {
    "id": 2067,
    "title": "Zinc 15mg Cobre 1mg: Ratio Crítico Inmunidad Longevidad",
    "primary_keyword": "zinc cobre ratio suplemento",
    "secondary_keywords": ["zinc picolinato vs bisglicinato", "zinc cobre balance", "zinc longevidad inmunidad"],
    "search_intent": "informational",
    "estimated_volume": "medium",
    "estimated_difficulty": "medium",
    "outline": ["H2: Importancia zinc-cobre", "H2: Ratio óptimo 15:1 zinc:cobre", "H2: Picolinato vs bisglicinato absorción", "H2: Prasad Adv Nutr 2013 inmunidad", "H2: Marcas que incluyen ratio", "H2: FAQ"],
    "key_points": ["Prasad Adv Nutr 2013 zinc inmunidad", "Suplementación zinc puede causar deficiencia cobre", "Ratio óptimo 15mg zinc : 1mg cobre", "Bisglicinato 43% absorción superior", "Picolinato segunda mejor opción"],
    "internal_link_suggestions": ["vitamina d3 k2 dosis"],
    "amazon_product_categories": ["Zinc bisglicinato", "Zinc cobre balance"],
    "monetization_intent": "affiliate_high",
    "schema_type": "Review",
    "estimated_word_count": 2700,
    "eeat_signal": "Prasad Adv Nutr 2013, Lukaski Am J Clin Nutr 1996"
  },
  {
    "id": 2068,
    "title": "Lp(a) Lipoproteína A: Marcador Genético Cardiovascular Oculto",
    "primary_keyword": "lipoproteina a lp(a)",
    "secondary_keywords": ["lp a alto que hacer", "lipoproteina a genética", "lp a niacina pcsk9"],
    "search_intent": "informational",
    "estimated_volume": "medium",
    "estimated_difficulty": "high",
    "outline": ["H2: Qué es Lp(a)", "H2: 100% genético, mide 1 vez vida", "H2: 20% población >50 mg/dL alto", "H2: Tsimikas JACC 2017", "H2: Tratamientos: PCSK9, niacina, lipoprotein apheresis", "H2: FAQ"],
    "key_points": ["Tsimikas JACC 2017 review completa", "Lp(a) 100% determinado genéticamente", "20% población >50 mg/dL riesgo elevado", "Estatinas no reducen, pueden aumentar", "Pelacarsen ensayo Phase 3 antisense"],
    "internal_link_suggestions": ["apob colesterol cardiovascular"],
    "amazon_product_categories": [],
    "monetization_intent": "adsense_only",
    "schema_type": "Article",
    "estimated_word_count": 3000,
    "eeat_signal": "Tsimikas JACC 2017, Nordestgaard JAMA 2009"
  },
  {
    "id": 2069,
    "title": "Tongkat Ali 200mg: Eurycoma Testosterona Cortisol Talbot 2013",
    "primary_keyword": "tongkat ali testosterona dosis",
    "secondary_keywords": ["eurycoma longifolia 200mg", "tongkat ali talbot estudio", "physta tongkat ali"],
    "search_intent": "transactional",
    "estimated_volume": "high",
    "estimated_difficulty": "medium",
    "outline": ["H2: Qué es Tongkat Ali", "H2: Talbot J Int Soc Sports Nutr 2013", "H2: Aumenta testosterona 37%", "H2: Reduce cortisol 16%", "H2: Physta vs LJ100 marcas", "H2: FAQ"],
    "key_points": ["Talbot J Int Soc Sports Nutr 2013 63 personas", "Aumenta testosterona libre 37%", "Reduce cortisol 16%", "Physta extracto patentado Malasia 200mg/día", "Ciclo 8 semanas / 4 descanso recomendado"],
    "internal_link_suggestions": ["ashwagandha ksm-66"],
    "amazon_product_categories": ["Tongkat Ali Physta", "Eurycoma longifolia"],
    "monetization_intent": "affiliate_high",
    "schema_type": "Review",
    "estimated_word_count": 2900,
    "eeat_signal": "Talbot J Int Soc Sports Nutr 2013, George 2013"
  },
  {
    "id": 2070,
    "title": "Fadogia Agrestis Huberman: Riesgos Hepatotoxicidad Real",
    "primary_keyword": "fadogia agrestis efectos",
    "secondary_keywords": ["fadogia huberman testosterona", "fadogia hígado riesgo", "fadogia tongkat ali stack"],
    "search_intent": "informational",
    "estimated_volume": "medium",
    "estimated_difficulty": "low",
    "outline": ["H2: Qué es Fadogia Agrestis", "H2: Huberman recomendación 2022", "H2: Estudio Yakubu rata 2008", "H2: Hepatotoxicidad y testicular", "H2: Por qué solo evidencia animal", "H2: FAQ"],
    "key_points": ["Huberman Lab podcast 2022 popularizó", "Yakubu Asian J Androl 2008 rata", "Solo evidencia animal, NO humanos", "Hepatotoxicidad ratas dosis altas", "Stack con Tongkat Ali sin estudios"],
    "internal_link_suggestions": ["tongkat ali testosterona"],
    "amazon_product_categories": [],
    "monetization_intent": "adsense_only",
    "schema_type": "Article",
    "estimated_word_count": 2700,
    "eeat_signal": "Yakubu Asian J Androl 2008, Huberman Stanford"
  },
  {
    "id": 2071,
    "title": "Magnesio Glicinato 400mg: Dosis Sueño Calmante GABA",
    "primary_keyword": "magnesio glicinato 400mg",
    "secondary_keywords": ["magnesio glicinato dormir mejor", "magnesio bisglicinato calidad", "glicinato vs malato"],
    "search_intent": "transactional",
    "estimated_volume": "high",
    "estimated_difficulty": "medium",
    "outline": ["H2: Qué es magnesio glicinato", "H2: Biodisponibilidad 80% top forma", "H2: Glicina sinérgica calmante", "H2: 400mg/noche protocolo sueño", "H2: Marcas TRACS verificadas", "H2: FAQ"],
    "key_points": ["Bisglicinato quelado biodisponibilidad 80%", "Glicina aporta GABA precursor calmante", "400mg/noche óptimo sueño", "Sin efectos laxantes vs óxido", "Coats J Reprod Med 1992 deficiencia 50%"],
    "internal_link_suggestions": ["magnesio treonato vs glicinato"],
    "amazon_product_categories": ["Magnesio glicinato 400mg", "Magnesio bisglicinato"],
    "monetization_intent": "affiliate_high",
    "schema_type": "Review",
    "estimated_word_count": 2700,
    "eeat_signal": "Coats J Reprod Med 1992, Schuette Magnesium 1989"
  },
  {
    "id": 2072,
    "title": "Cromo Picolinato 200mcg: Glucosa Antojos Anderson 1997",
    "primary_keyword": "cromo picolinato glucosa",
    "secondary_keywords": ["cromo picolinato dosis", "anderson cromo diabetes", "cromo antojos azucar"],
    "search_intent": "transactional",
    "estimated_volume": "medium",
    "estimated_difficulty": "low",
    "outline": ["H2: Qué es cromo picolinato", "H2: Anderson Diabetes 1997", "H2: Mejora sensibilidad insulina 30%", "H2: 200-1000mcg dosis según uso", "H2: Reduce antojos carbohidratos", "H2: FAQ"],
    "key_points": ["Anderson Diabetes 1997 180 chinos", "1000mcg/día mejoró HbA1c", "Aumenta receptores insulina 50%", "Picolinato 5x absorción vs cloruro", "Reduce antojos carbo 65% Docherty 2005"],
    "internal_link_suggestions": ["berberina dosis longevidad"],
    "amazon_product_categories": ["Cromo picolinato 200mcg", "Cromo Niacin"],
    "monetization_intent": "affiliate_high",
    "schema_type": "Review",
    "estimated_word_count": 2500,
    "eeat_signal": "Anderson Diabetes 1997, Docherty J Psychiatr Pract 2005"
  },
  {
    "id": 2073,
    "title": "Inositol 4g: Mioinositol PCOS Insulina Costantini 2013",
    "primary_keyword": "mioinositol 4g pcos",
    "secondary_keywords": ["mioinositol vs d-chiro", "inositol resistencia insulina", "inositol estudio costantini"],
    "search_intent": "transactional",
    "estimated_volume": "medium",
    "estimated_difficulty": "medium",
    "outline": ["H2: Qué es mioinositol", "H2: Costantini Eur Rev Med 2013 PCOS", "H2: 4g + 100mg ácido fólico ratio 40:1", "H2: D-chiro-inositol 100mg sinergia", "H2: Mejora sensibilidad insulina", "H2: FAQ"],
    "key_points": ["Costantini Eur Rev 2013 PCOS", "Ratio 40:1 mioinositol:D-chiro óptimo", "4g/día + 100mg ácido fólico", "Mejora ovulación 88% PCOS 6 meses", "Reduce ansiedad y ataques pánico Palatnik 2001"],
    "internal_link_suggestions": ["cromo picolinato glucosa"],
    "amazon_product_categories": ["Mioinositol 4g polvo", "Inositol 40:1"],
    "monetization_intent": "affiliate_high",
    "schema_type": "Review",
    "estimated_word_count": 2800,
    "eeat_signal": "Costantini Eur Rev Med 2013, Palatnik J Clin Psychopharmacol 2001"
  },
  {
    "id": 2074,
    "title": "Zona 2 Cardio 180-Edad: Mitocondrial San Millan Attia",
    "primary_keyword": "zona 2 cardio 180 edad",
    "secondary_keywords": ["maffetone formula 180 edad", "zona 2 mitocondrial san millan", "cardio low intensity"],
    "search_intent": "informational",
    "estimated_volume": "medium",
    "estimated_difficulty": "medium",
    "outline": ["H2: Qué es Zona 2", "H2: Fórmula Maffetone 180-edad", "H2: San Millan Front Physiol 2018", "H2: Mejora flexibilidad metabólica", "H2: 4 horas/semana protocolo Attia", "H2: FAQ"],
    "key_points": ["Maffetone fórmula 180-edad", "San Millan UC Boulder 2018", "Aumenta densidad mitocondrial músculos", "Quema grasa principalmente", "Attia recomienda 4h/semana mínimo"],
    "internal_link_suggestions": ["vo2 max longevidad"],
    "amazon_product_categories": ["Pulsómetro Polar H10", "Reloj Garmin Fenix"],
    "monetization_intent": "both",
    "schema_type": "HowTo",
    "estimated_word_count": 3000,
    "eeat_signal": "San Millan Front Physiol 2018, Maffetone Big Book"
  },
  {
    "id": 2075,
    "title": "Centenarian Decathlon Attia: 10 Pruebas Físicas a los 90",
    "primary_keyword": "centenarian decathlon attia",
    "secondary_keywords": ["pruebas físicas 90 años", "attia 10 metas longevidad", "outlive decathlon"],
    "search_intent": "informational",
    "estimated_volume": "low",
    "estimated_difficulty": "low",
    "outline": ["H2: Concepto Centenarian Decathlon", "H2: 10 metas físicas a los 90", "H2: Trabajar hacia atrás desde objetivo", "H2: Fuerza cargar 10kg cada brazo", "H2: Levantarse del suelo sin manos", "H2: FAQ"],
    "key_points": ["Attia Outlive 2023 capítulo central", "10 actividades específicas a 90 años", "Cargar 10kg cada mano subir escaleras", "Squat con 25% peso corporal", "Levantarse suelo sin usar manos"],
    "internal_link_suggestions": ["peter attia plan medico"],
    "amazon_product_categories": ["Mancuernas ajustables", "Banda resistencia kit"],
    "monetization_intent": "both",
    "schema_type": "HowTo",
    "estimated_word_count": 2900,
    "eeat_signal": "Attia Outlive 2023, NSCA Strength Cond"
  },
  {
    "id": 2076,
    "title": "Apolipoproteína E APOE4: Riesgo Alzheimer Genética Test",
    "primary_keyword": "apoe4 genética alzheimer",
    "secondary_keywords": ["apoe4 test casa", "apoe4 dieta tratamiento", "apoe4 homocigoto riesgo"],
    "search_intent": "informational",
    "estimated_volume": "medium",
    "estimated_difficulty": "high",
    "outline": ["H2: Qué es APOE4", "H2: Corder Science 1993", "H2: Heterocigoto 3x riesgo, homocigoto 12x", "H2: 23andMe vs Promethease test", "H2: Estrategias específicas APOE4", "H2: FAQ"],
    "key_points": ["Corder Science 1993", "Homocigoto APOE4/4 12x riesgo Alzheimer", "Heterocigoto 3-4x riesgo", "23andMe incluye en test 99€", "Bredesen Aging 2014 protocolo personalizado"],
    "internal_link_suggestions": ["dieta mind alzheimer"],
    "amazon_product_categories": ["Test ADN 23andMe", "MyHeritage DNA"],
    "monetization_intent": "both",
    "schema_type": "Article",
    "estimated_word_count": 3100,
    "eeat_signal": "Corder Science 1993, Bredesen Aging 2014"
  },
  {
    "id": 2077,
    "title": "Hormesis Concepto: Estrés Bajo Activa Defensas Mattson 2008",
    "primary_keyword": "hormesis longevidad mattson",
    "secondary_keywords": ["hormesis ejemplos cuerpo", "estres bueno celular", "xenohormesis polifenoles"],
    "search_intent": "informational",
    "estimated_volume": "low",
    "estimated_difficulty": "medium",
    "outline": ["H2: Qué es la hormesis", "H2: Mattson Ann N Y Acad Sci 2008", "H2: Ejemplos: ejercicio, ayuno, sauna, frío", "H2: Xenohormesis polifenoles plantas", "H2: Aplicación práctica protocolo", "H2: FAQ"],
    "key_points": ["Mattson Ann N Y Acad Sci 2008 hormesis", "Estresor bajo activa defensas: AMPK, sirtuinas, Nrf2", "Ejercicio, ayuno, sauna, frío principales", "Xenohormesis: estrés plantas → polifenoles → humanos", "Howitz Nature 2008 xenohormesis hipótesis"],
    "internal_link_suggestions": ["sauna finlandesa protocolo", "cold plunge huberman"],
    "amazon_product_categories": ["Libro Mattson Mind Sleep"],
    "monetization_intent": "both",
    "schema_type": "Article",
    "estimated_word_count": 2900,
    "eeat_signal": "Mattson Ann N Y Acad Sci 2008, Howitz Nature 2008"
  },
  {
    "id": 2078,
    "title": "Marcadores Inflamación Crónica: hsCRP Homocisteína Test",
    "primary_keyword": "hscrp homocisteina marcadores inflamacion",
    "secondary_keywords": ["proteina c reactiva ultrasensible", "homocisteina valores normales", "inflamacion silenciosa test"],
    "search_intent": "informational",
    "estimated_volume": "medium",
    "estimated_difficulty": "high",
    "outline": ["H2: Qué es inflamación silenciosa", "H2: hsCRP <1 ideal, <3 medio", "H2: Homocisteína <8 μmol/L", "H2: Ridker NEJM 2008 JUPITER", "H2: Cómo reducir naturalmente", "H2: FAQ"],
    "key_points": ["Ridker NEJM 2008 JUPITER 17802 personas", "hsCRP <1 mg/L ideal, >3 alto riesgo", "Homocisteína <8 μmol/L target óptimo", "Folato + B12 + B6 reducen homocisteína", "Omega 3 reducen hsCRP 25%"],
    "internal_link_suggestions": ["omega 3 epa dha", "metilcobalamina b12"],
    "amazon_product_categories": ["B12 metilcobalamina", "Folato 5-MTHF"],
    "monetization_intent": "both",
    "schema_type": "Article",
    "estimated_word_count": 3000,
    "eeat_signal": "Ridker NEJM 2008 JUPITER, Wald BMJ 2002"
  },
  {
    "id": 2079,
    "title": "Senescencia Celular: Células Zombie SASP Campisi 2007",
    "primary_keyword": "senescencia celular zombie",
    "secondary_keywords": ["sasp inflamacion senescente", "campisi cell senescence", "celulas senescentes envejecimiento"],
    "search_intent": "informational",
    "estimated_volume": "low",
    "estimated_difficulty": "high",
    "outline": ["H2: Qué es senescencia celular", "H2: Campisi Annu Rev Physiol 2013", "H2: SASP factor inflamatorio crónico", "H2: Acumulación 5% tejidos al envejecer", "H2: Senolíticos como terapia", "H2: FAQ"],
    "key_points": ["Campisi Annu Rev Physiol 2013", "SASP: senescence-associated secretory phenotype", "Células zombie no mueren ni dividen", "5-15% tejidos viejos vs 1% jóvenes", "Senolíticos eliminan selectivamente"],
    "internal_link_suggestions": ["fisetin senolitico", "dasatinib quercetina"],
    "amazon_product_categories": [],
    "monetization_intent": "adsense_only",
    "schema_type": "Article",
    "estimated_word_count": 3000,
    "eeat_signal": "Campisi Annu Rev Physiol 2013, Coppe PLoS Biol 2008"
  },
  {
    "id": 2080,
    "title": "Bryan Johnson Blueprint: Análisis Real Protocolo $2M Año",
    "primary_keyword": "bryan johnson blueprint protocolo",
    "secondary_keywords": ["bryan johnson dieta", "blueprint suplementos lista", "johnson reverso edad"],
    "search_intent": "informational",
    "estimated_volume": "high",
    "estimated_difficulty": "low",
    "outline": ["H2: Quién es Bryan Johnson", "H2: Protocolo Blueprint completo", "H2: 100+ suplementos diarios", "H2: Dieta vegana 1977 kcal", "H2: Coste 2M USD anual", "H2: FAQ"],
    "key_points": ["Johnson Project Blueprint 2021", "Tomó 100+ suplementos diarios", "Dieta vegana 1977 kcal estricta", "Test edad biológica reducida 5+ años", "Coste 2 millones USD/año documentado"],
    "internal_link_suggestions": ["test edad biologica metilacion"],
    "amazon_product_categories": ["Suplementos longevidad mix"],
    "monetization_intent": "both",
    "schema_type": "Article",
    "estimated_word_count": 3200,
    "eeat_signal": "Johnson Blueprint público GitHub, datos verificados Time 2023"
  },
  {
    "id": 2081,
    "title": "Glucagon-Like Peptide 1 Natural: Aumentar GLP-1 Sin Ozempic",
    "primary_keyword": "glp-1 aumentar natural",
    "secondary_keywords": ["alternativa natural ozempic", "glp-1 fibra alimentos", "berberina vs ozempic"],
    "search_intent": "informational",
    "estimated_volume": "high",
    "estimated_difficulty": "medium",
    "outline": ["H2: Qué es GLP-1", "H2: Estrategias dietéticas naturales", "H2: Fibra fermentable AGCC butirato", "H2: Yerba mate Pereira 2013", "H2: Berberina como alternativa", "H2: FAQ"],
    "key_points": ["GLP-1 Glucagon-Like Peptide 1 incretina", "Fibra fermentable produce butirato → GLP-1", "Pereira Phytomedicine 2013 yerba mate", "Berberina aumenta GLP-1 vía AMPK", "Proteína primero comida estimula GLP-1"],
    "internal_link_suggestions": ["berberina dosis longevidad"],
    "amazon_product_categories": ["Yerba mate orgánica", "Fibra psyllium"],
    "monetization_intent": "both",
    "schema_type": "HowTo",
    "estimated_word_count": 3000,
    "eeat_signal": "Pereira Phytomedicine 2013, Yu Acta Pharmacol Sin 2010"
  },
  {
    "id": 2082,
    "title": "Mitocondria Biogénesis: PGC-1α Activadores Naturales 2024",
    "primary_keyword": "mitocondria biogenesis natural",
    "secondary_keywords": ["pgc-1 alfa activadores", "biogenesis mitocondrial ejercicio", "nuevas mitocondrias"],
    "search_intent": "informational",
    "estimated_volume": "low",
    "estimated_difficulty": "high",
    "outline": ["H2: Qué es PGC-1α", "H2: Master regulador biogénesis", "H2: Ejercicio HIIT activa más", "H2: PQQ resveratrol cetonas", "H2: Frío activa BAT mitocondrias", "H2: FAQ"],
    "key_points": ["PGC-1α coactivador transcripción", "Lin Cell Metab 2005 biogénesis", "HIIT activa PGC-1α x10 vs steady state", "PQQ activa CREB → PGC-1α", "Frío activa BAT mitocondrias termogénesis"],
    "internal_link_suggestions": ["pqq mitocondrial", "zona 2 cardio"],
    "amazon_product_categories": ["PQQ MitoLife", "CoQ10 Ubiquinol"],
    "monetization_intent": "affiliate_high",
    "schema_type": "Article",
    "estimated_word_count": 2900,
    "eeat_signal": "Lin Cell Metab 2005, Liu Aging Cell 2019"
  },
  {
    "id": 2083,
    "title": "NAD+ Niveles Edad: Medición Caída Verdadera Imai 2014",
    "primary_keyword": "nad+ niveles edad caida",
    "secondary_keywords": ["nad+ medicion test", "imai nad declive", "nad+ ejercicio sirtuinas"],
    "search_intent": "informational",
    "estimated_volume": "medium",
    "estimated_difficulty": "high",
    "outline": ["H2: Qué es NAD+", "H2: Imai Nature Cell Biol 2014", "H2: Caída 50% a los 60 años", "H2: Métodos medición precisos", "H2: NMN NR vs ejercicio HIIT", "H2: FAQ"],
    "key_points": ["Imai Nature Cell Biol 2014 declive NAD+", "NAD+ cae 50% entre 30-60 años", "Test sangre NAD+ 200€ ChromaDex", "HIIT aumenta NAD+ 25-50%", "Ejercicio gratis vs NMN 100€/mes"],
    "internal_link_suggestions": ["nmn nr longevidad"],
    "amazon_product_categories": ["NMN sublingual", "Test NAD+ casa"],
    "monetization_intent": "affiliate_high",
    "schema_type": "Article",
    "estimated_word_count": 3100,
    "eeat_signal": "Imai Nature Cell Biol 2014, Yoshino Cell Metab 2018"
  },
  {
    "id": 2084,
    "title": "Buettner 9 Power Lessons: Síntesis Blue Zones National Geo",
    "primary_keyword": "buettner 9 lecciones blue zones",
    "secondary_keywords": ["power 9 longevidad", "blue zones lecciones aplicar", "buettner reglas longevidad"],
    "search_intent": "informational",
    "estimated_volume": "medium",
    "estimated_difficulty": "low",
    "outline": ["H2: Buettner Power 9 framework", "H2: Movimiento natural diario", "H2: Propósito ikigai/plan vida", "H2: Reducir estrés rituales", "H2: Comunidad fe familia", "H2: FAQ"],
    "key_points": ["Buettner National Geographic 2008 Power 9", "Movimiento natural sin gimnasio", "80% rule (Hara Hachi Bu)", "Plant slant 95% dieta vegetal", "Wine at 5 moderado social"],
    "internal_link_suggestions": ["sardinia zona azul", "okinawa hara hachi bu"],
    "amazon_product_categories": ["Blue Zones libro Buettner", "Aceite oliva DOP"],
    "monetization_intent": "both",
    "schema_type": "Article",
    "estimated_word_count": 3000,
    "eeat_signal": "Buettner National Geographic 2008 Blue Zones"
  },
  {
    "id": 2085,
    "title": "Step Protocol Longevidad Diaria: Routine Atia Sinclair Mix",
    "primary_keyword": "rutina diaria longevidad",
    "secondary_keywords": ["protocolo paso a paso longevidad", "rutina antiaging mañana", "stack suplementos sinclair"],
    "search_intent": "informational",
    "estimated_volume": "medium",
    "estimated_difficulty": "low",
    "outline": ["H2: Mañana 5:30-7:00", "H2: Mediodía 12-14h", "H2: Tarde 17-19h", "H2: Noche 21-23h", "H2: Stack suplementos día completo", "H2: FAQ"],
    "key_points": ["Café negro + L-teanina 200mg al despertar", "Sol 10 min ojos sin gafas DLMO", "NMN 1g + resveratrol 500mg + yogur grasa", "Zona 2 cardio 45 min mediodía", "Magnesio glicinato 400mg + glicina 3g antes dormir"],
    "internal_link_suggestions": ["peter attia plan medico", "protocolo sinclair"],
    "amazon_product_categories": ["Stack longevidad starter", "Báscula corporal"],
    "monetization_intent": "affiliate_high",
    "schema_type": "HowTo",
    "estimated_word_count": 3200,
    "eeat_signal": "Sinclair Lifespan 2019, Attia Outlive 2023, Huberman Protocols"
  },
  {
    "id": 2086,
    "title": "Mythbusting NMN Sublingual vs Oral: Evidencia Real 2024",
    "primary_keyword": "nmn sublingual vs oral",
    "secondary_keywords": ["nmn absorcion mejor forma", "nmn sublingual mito", "nmn liposomal"],
    "search_intent": "comparative",
    "estimated_volume": "medium",
    "estimated_difficulty": "medium",
    "outline": ["H2: Disputa NMN absorción", "H2: Yoshino Cell Metab 2021 oral funciona", "H2: Sublingual marketing sin estudios humanos", "H2: Liposomal evidencia limitada", "H2: Marcas con resultados real", "H2: FAQ"],
    "key_points": ["Yoshino Cell Metab 2021 oral aumenta NAD+", "Sublingual marketing sin estudios validados", "Liposomal Renue By Science Phase 1 2023", "1g/día oral evidencia más sólida", "Tomar mañana por activación SIRT1"],
    "internal_link_suggestions": ["nmn nr longevidad"],
    "amazon_product_categories": ["NMN oral 500mg", "NMN liposomal"],
    "monetization_intent": "affiliate_high",
    "schema_type": "Review",
    "estimated_word_count": 2800,
    "eeat_signal": "Yoshino Cell Metab 2021, Yoshino Endocr Rev 2018"
  },
  {
    "id": 2087,
    "title": "Microbiota Test Casa: uBiome Viome Atlas Comparativa 2024",
    "primary_keyword": "test microbiota casa comparativa",
    "secondary_keywords": ["viome vs atlas biomed", "test heces microbioma", "akkermansia diversidad test"],
    "search_intent": "comparative",
    "estimated_volume": "medium",
    "estimated_difficulty": "high",
    "outline": ["H2: Por qué testear microbiota", "H2: Viome RNA 16S vs Atlas DNA", "H2: Indicadores diversidad clave", "H2: Akkermansia ratio Bacteroides", "H2: Coste 200-400€ por test", "H2: FAQ"],
    "key_points": ["Viome metratranscriptómico 200 USD", "Atlas Biomed 16S DNA 99 USD", "InnerBuddies microbioma diversidad", "Akkermansia >2% indicador salud", "Ratio Firmicutes/Bacteroidetes peso"],
    "internal_link_suggestions": ["akkermansia muciniphila"],
    "amazon_product_categories": [],
    "monetization_intent": "adsense_only",
    "schema_type": "Review",
    "estimated_word_count": 3100,
    "eeat_signal": "Lloyd-Price Nature 2017 metaanálisis, Sender PLoS Biol 2016"
  },
  {
    "id": 2088,
    "title": "Estrés Crónico Cortisol: Telómeros Acortados Epel PNAS 2004",
    "primary_keyword": "estres cortisol telomeros",
    "secondary_keywords": ["epel pnas estres telomeros", "cortisol envejecimiento celular", "manejar estres longevidad"],
    "search_intent": "informational",
    "estimated_volume": "medium",
    "estimated_difficulty": "medium",
    "outline": ["H2: Epel PNAS 2004 madres cuidadoras", "H2: Cortisol crónico acorta telómeros 10 años", "H2: HPA axis disregulación", "H2: HRV biomarcador resiliencia", "H2: Intervenciones meditación yoga", "H2: FAQ"],
    "key_points": ["Epel PNAS 2004 estudio histórico telómeros estrés", "Madres cuidadoras hijo enfermo crónico", "Telómeros 10 años más viejos celularmente", "HRV >50ms indicador resiliencia", "MBSR 8 semanas restaura HRV"],
    "internal_link_suggestions": ["meditacion mbsr 8 semanas", "telomeros ejercicio hiit"],
    "amazon_product_categories": ["Reloj HRV Whoop", "Cojín meditación"],
    "monetization_intent": "both",
    "schema_type": "Article",
    "estimated_word_count": 3000,
    "eeat_signal": "Epel PNAS 2004, Blackburn Nobel 2009"
  },
  {
    "id": 2089,
    "title": "Diabetes Tipo 2 Reversible: Estudio DiRECT Lean Lancet 2018",
    "primary_keyword": "diabetes tipo 2 reversible",
    "secondary_keywords": ["direct lean lancet 2018", "remision diabetes 2 dieta", "diabetes reversion 800 calorias"],
    "search_intent": "informational",
    "estimated_volume": "high",
    "estimated_difficulty": "high",
    "outline": ["H2: DiRECT trial Lean 2018", "H2: 800 kcal 12-20 semanas", "H2: Remisión 46% pacientes año 1", "H2: Mecanismo: vaciado grasa hepática", "H2: Reintroducción alimentos protocolo", "H2: FAQ"],
    "key_points": ["Lean Lancet 2018 DiRECT trial 298 personas", "46% remisión año 1, 36% año 2", "800 kcal/día batidos 12-20 semanas", "Vaciado grasa hepática pancreática", "Pérdida >15kg = 86% remisión"],
    "internal_link_suggestions": ["fmd ayuno mimetico longo"],
    "amazon_product_categories": ["Báscula corporal precisa", "Glucómetro continuo"],
    "monetization_intent": "both",
    "schema_type": "Article",
    "estimated_word_count": 3200,
    "eeat_signal": "Lean Lancet 2018 DiRECT, Taylor Diabetologia 2008"
  }
]
